Workbook

Sheet Phase Planning
J2: SM2 Alg
B3: Article ID | C3: Content | D3: Interest 1 | E3: Interest 2 | F3: Interest 3 | G3: SM2 Tag | J3: 1 | K3: Fruits
B4: 1 | C4: Cooking Video | D4: Food | E4: Italian | G4: Food | J4: 2 | K4: Location
B5: 2 | C5: Travel Vlog | D5: Location | E5: Food | G5: Location | J5: 3 | K5: Season
B6: 3 | C6: Story time with dog | D6: mood | E6: animal | F6: Location | G6: Mood | J6: 4 | K6: Mood
B7: 4 | C7: History educational content | D7: Location | E7: History | G7: Past/Present/Future | J7: 5 | K7: Plants
J8: 6 | K8: Animals
J9: 7 | K9: Kitchen
J10: 8 | K10: Past/Present/Future
B13: Phase 1
B14: Current | C14: Articles and Translated | N14: Elo System
B15: 1 | C15: Frequency Dictionary | D15: Database of Frequency Dictionary | E15: Catorgoried with Tags | G15: Issac, Milan, Alex | N15: First 10 | O15: Rank
B16: 2 | C16: Quizes interact with DB | D16: criteria of a good quiz | E16: Make a prompt for quiz generation | J16: Novice | K16: 0
B17: 3 | C17: Impliment Quiz into product | J17: Beg | K17: 300
J18: Inter | K18: 600
B19: 4 | C19: Quizes with articles with key words with SM2 Algorithmn | J19: Pro | K19: 1000
B21: Key Dev
C22: Cost effective AI models
C23: Linking Frequency table to articles | F23: 3 | G23: 0.65 | H23: =F23*G23 -> 1.95
C24: Quiz to AI Model, cost effective, w prompt with article ID | D24: Click on article -> Starts prompt on Quiz | F24: 2 | G24: 0.35 | H24: =F24*G24 -> 0.7
C25: Elo based system quizes profile | D25: Milan and Issac Architecture | E25: Starting elo | F25: 300
E26: plus quiz | H26: =SUM(H23:H24) -> 2.65
E27: Beg | F27: 10
E28: Adv | F28: 30
B31: Phase 2 | C31: Quiz talks to SM2 based on Score | E31: Spanish, French, Japanese, Korean, and German
C32: Dialects

Sheet Words
A2: Wordopedia | B2: rank | C2: word | D2: absolute frequency | E2: lemma forms | I2: Word Dictionary | J2: https://wortschatz.uni-leipzig.de/en/download/spa
B4: 101 | C4: de | D4: 15226 | I4: The Leipzig Corpora Collection (University of Leipzig) is highly credible and considered one of the premier resources in the field of computational linguistics. Within academic and data science circles, it is a standard source for word frequency data.
B5: 102 | C5: la | D5: 7493
B6: 103 | C6: en | D6: 5973 | I6: University of Leipzig
B7: 104 | C7: el | D7: 5435
B8: 105 | C8: y | D8: 5422
B9: 106 | C9: que | D9: 4171
B10: 107 | C10: a | D10: 3844 | J10: CATEGORYS
B11: 108 | C11: se | D11: 2845
B12: 109 | C12: los | D12: 2800 | J12: Category ID | K12: Category Name
B13: 110 | C13: del | D13: 2645 | J13: 1 | K13: Politics & Government
B14: 111 | C14: un | D14: 2205 | J14: 2 | K14: Economics & Business
B15: 112 | C15: su | D15: 2051 | J15: 3 | K15: Arts, Culture & Entertainment
B16: 113 | C16: una | D16: 2023 | J16: 4 | K16: Sports
B17: 114 | C17: con | D17: 2014 | J17: 5 | K17: Science, Technology & Health
B18: 115 | C18: las | D18: 1946 | J18: 6 | K18: Geography & Nature
B19: 116 | C19: por | D19: 1899 | J19: 7 | K19: Education & Research
B20: 117 | C20: para | D20: 1498 | J20: 8 | K20: Law & Security
B21: 118 | C21: es | D21: 1206 | J21: 9 | K21: Religion & History
B22: 119 | C22: El | D22: 1182
B23: 120 | C23: como | D23: 1140
B24: 121 | C24: al | D24: 1055
B25: 122 | C25: En | D25: 999
B26: 123 | C26: fue | D26: 944
B27: 124 | C27: no | D27: 891
B28: 125 | C28: La | D28: 879
B29: 126 | C29: más | D29: 855
B30: 127 | C30: sus | D30: 663
B31: 128 | C31: lo | D31: 652
B32: 129 | C32: o | D32: 458
B33: 130 | C33: también | D33: 390
... B182: 279 | C182: zona | D182: 81
B183: 280 | C183: 10 | D183: 80
B184: 281 | C184: Cuando | D184: 80
B185: 282 | C185: San | D185: 80
B186: 283 | C186: además | D186: 80
B187: 284 | C187: dentro | D187: 80
B188: 285 | C188: mayoría | D188: 80
B189: 286 | C189: muchos | D189: 80
B190: 287 | C190: poco | D190: 80
B191: 288 | C191: poder | D191: 80
B192: 289 | C192: último | D192: 80
B193: 290 | C193: Con | D193: 79
B194: 291 | C194: bien | D194: 79
B195: 292 | C195: habían | D195: 79
... B237: 334 | C237: junio | D237: 67
B238: 335 | C238: 1 | D238: 66
B239: 336 | C239: algunas | D239: 66
B240: 337 | C240: lado | D240: 66
B241: 338 | C241: uso | D241: 66
B242: 339 | C242: 2 | D242: 65
B243: 340 | C243: Estados | D243: 65
B244: 341 | C244: carrera | D244: 65
B245: 342 | C245: conocido | D245: 65
B246: 343 | C246: desarrollo | D246: 65
B247: 344 | C247: hacer | D247: 65
B248: 345 | C248: julio | D248: 65
B249: 346 | C249: septiembre | D249: 65
B250: 347 | C250: convirtió | D250: 64
B251: 348 | C251: diciembre | D251: 64
B252: 349 | C252: fuera | D252: 64
B253: 350 | C253: segunda | D253: 64
B254: 351 | C254: todas | D254: 64
... B266: 363 | C266: tras | D266: 61
B267: 364 | C267: 3 | D267: 60
B268: 365 | C268: les | D268: 60
B269: 366 | C269: noviembre | D269: 60
B270: 367 | C270: producción | D270: 60
B271: 368 | C271: siempre | D271: 60
B272: 369 | C272: título | D272: 60
B273: 370 | C273: ver | D273: 60
B274: 371 | C274: canción | D274: 59
B275: 372 | C275: versión | D275: 59
B276: 373 | C276: aún | D276: 58
B277: 374 | C277: da | D277: 58
B278: 375 | C278: estudios | D278: 58
B279: 376 | C279: mucho | D279: 58
... B297: 394 | C297: tener | D297: 56
B298: 395 | C298: 15 | D298: 55
B299: 396 | C299: 2009 | D299: 55
B300: 397 | C300: 4 | D300: 55
B301: 398 | C301: Como | D301: 55
B302: 399 | C302: cinco | D302: 55
B303: 400 | C303: hombre | D303: 55
B304: 401 | C304: marzo | D304: 55
B305: 402 | C305: partido | D305: 55
B306: 403 | C306: proyecto | D306: 55
B307: 404 | C307: río | D307: 55
B308: 405 | C308: toda | D308: 55
B309: 406 | C309: 8 | D309: 54
B310: 407 | C310: acuerdo | D310: 54
B311: 408 | C311: cerca | D311: 54
B312: 409 | C312: color | D312: 54
B313: 410 | C313: nunca | D313: 54
B314: 411 | C314: público | D314: 54
B315: 412 | C315: Pero | D315: 53
B316: 413 | C316: cantidad | D316: 53
B317: 414 | C317: nacional | D317: 53
B318: 415 | C318: meses | D318: 52
B319: 416 | C319: muchas | D319: 52
...

Sheet Sheet3
B2: Wordopedia | C2: WORD ID | D2: word | E2: absolute frequency | F2: CAT ID | G2: LEVEL ID | J2: Word Dictionary | K2: https://wortschatz.uni-leipzig.de/en/download/spa
C4: 1 | D4: de | E4: 15226 | F4: =_xlfn.XLOOKUP(D4,'Gemini Output'!B:B,'Gemini Output'!C:C,"No Match Yet") -> 1 | G4: =_xlfn.XLOOKUP(D4,'Gemini Output'!B:B,'Gemini Output'!E:E,"No Match Yet") -> L1 | J4: The Leipzig Corpora Collection (University of Leipzig) is highly credible and considered one of the premier resources in the field of computational linguistics. Within academic and data science circles, it is a standard source for word frequency data.
C5: 2 | D5: la | E5: 7493 | F5: =_xlfn.XLOOKUP(D5,'Gemini Output'!B:B,'Gemini Output'!C:C,"No Match Yet") -> 12 | G5: =_xlfn.XLOOKUP(D5,'Gemini Output'!B:B,'Gemini Output'!E:E,"No Match Yet") -> L1
C6: 3 | D6: en | E6: 5973 | F6: =_xlfn.XLOOKUP(D6,'Gemini Output'!B:B,'Gemini Output'!C:C,"No Match Yet") -> 10 | G6: =_xlfn.XLOOKUP(D6,'Gemini Output'!B:B,'Gemini Output'!E:E,"No Match Yet") -> L1 | J6: University of Leipzig
C7: 4 | D7: el | E7: 5435 | F7: =_xlfn.XLOOKUP(D7,'Gemini Output'!B:B,'Gemini Output'!C:C,"No Match Yet") -> 12 | G7: =_xlfn.XLOOKUP(D7,'Gemini Output'!B:B,'Gemini Output'!E:E,"No Match Yet") -> L1
C8: 5 | D8: y | E8: 5422 | F8: =_xlfn.XLOOKUP(D8,'Gemini Output'!B:B,'Gemini Output'!C:C,"No Match Yet") -> 12 | G8: =_xlfn.XLOOKUP(D8,'Gemini Output'!B:B,'Gemini Output'!E:E,"No Match Yet") -> L1
C9: 6 | D9: que | E9: 4171 | F9: =_xlfn.XLOOKUP(D9,'Gemini Output'!B:B,'Gemini Output'!C:C,"No Match Yet") -> 12 | G9: =_xlfn.XLOOKUP(D9,'Gemini Output'!B:B,'Gemini Output'!E:E,"No Match Yet") -> L1 | J9: CAT ID | K9: Category Name | L9: Quiz "Vibe" for the AI | R9: CAT ID | S9: COUNT of Filter | T9: Level Break down
C10: 7 | D10: a | E10: 3844 | F10: =_xlfn.XLOOKUP(D10,'Gemini Output'!B:B,'Gemini Output'!C:C,"No Match Yet") -> 13 | G10: =_xlfn.XLOOKUP(D10,'Gemini Output'!B:B,'Gemini Output'!E:E,"No Match Yet") -> L1 | J10: 1 | K10: Politics & Government | L10: Fact-based (Who, what law, which year?) | R10: 1 | S10: =COUNTIF(F:F,R10) -> 96 | T10: L1 | U10: =COUNTIF(G:G,T10) -> 452 | V10: =U10/1000 -> 0.452
C11: 8 | D11: se | E11: 2845 | F11: =_xlfn.XLOOKUP(D11,'Gemini Output'!B:B,'Gemini Output'!C:C,"No Match Yet") -> 12 | G11: =_xlfn.XLOOKUP(D11,'Gemini Output'!B:B,'Gemini Output'!E:E,"No Match Yet") -> L1 | J11: 2 | K11: Economy & Finance | L11: Logical/Numerical (Prices, growth, trends) | R11: 2 | S11: =COUNTIF(F:F,R11) -> 54 | T11: L2 | U11: =COUNTIF(G:G,T11) -> 486 | V11: =U11/1000 -> 0.486
C12: 9 | D12: los | E12: 2800 | F12: =_xlfn.XLOOKUP(D12,'Gemini Output'!B:B,'Gemini Output'!C:C,"No Match Yet") -> 12 | G12: =_xlfn.XLOOKUP(D12,'Gemini Output'!B:B,'Gemini Output'!E:E,"No Match Yet") -> L1 | J12: 3 | K12: Arts & Entertainment | L12: Creative/Recall (Names, works, dates) | R12: 3 | S12: =COUNTIF(F:F,R12) -> 67 | T12: L3 | U12: =COUNTIF(G:G,T12) -> 62 | V12: =U12/1000 -> 0.062
C13: 10 | D13: del | E13: 2645 | F13: =_xlfn.XLOOKUP(D13,'Gemini Output'!B:B,'Gemini Output'!C:C,"No Match Yet") -> 1 | G13: =_xlfn.XLOOKUP(D13,'Gemini Output'!B:B,'Gemini Output'!E:E,"No Match Yet") -> L1 | J13: 4 | K13: Sports | L13: Statistic/Outcome (Scores, teams, events) | R13: 4 | S13: =COUNTIF(F:F,R13) -> 46
C14: 11 | D14: un | E14: 2205 | F14: =_xlfn.XLOOKUP(D14,'Gemini Output'!B:B,'Gemini Output'!C:C,"No Match Yet") -> 12 | G14: =_xlfn.XLOOKUP(D14,'Gemini Output'!B:B,'Gemini Output'!E:E,"No Match Yet") -> L1 | J14: 5 | K14: Business & Labor | L14: Operational (Company names, hiring, trade) | R14: 5 | S14: =COUNTIF(F:F,R14) -> 59
C15: 12 | D15: su | E15: 2051 | F15: =_xlfn.XLOOKUP(D15,'Gemini Output'!B:B,'Gemini Output'!C:C,"No Match Yet") -> 5 | G15: =_xlfn.XLOOKUP(D15,'Gemini Output'!B:B,'Gemini Output'!E:E,"No Match Yet") -> L1 | J15: 6 | K15: Science & Tech | L15: Conceptual (How it works, discovery) | R15: 6 | S15: =COUNTIF(F:F,R15) -> 79
C16: 13 | D16: una | E16: 2023 | F16: =_xlfn.XLOOKUP(D16,'Gemini Output'!B:B,'Gemini Output'!C:C,"No Match Yet") -> 12 | G16: =_xlfn.XLOOKUP(D16,'Gemini Output'!B:B,'Gemini Output'!E:E,"No Match Yet") -> L1 | J16: 7 | K16: Education | L16: Institutional (Degrees, academic research) | R16: 7 | S16: =COUNTIF(F:F,R16) -> 44
C17: 14 | D17: con | E17: 2014 | F17: =_xlfn.XLOOKUP(D17,'Gemini Output'!B:B,'Gemini Output'!C:C,"No Match Yet") -> 12 | G17: =_xlfn.XLOOKUP(D17,'Gemini Output'!B:B,'Gemini Output'!E:E,"No Match Yet") -> L1 | J17: 8 | K17: Crime, Law & Justice | L17: Narrative (What happened, what was the ruling?) | R17: 8 | S17: =COUNTIF(F:F,R17) -> 41
C18: 15 | D18: las | E18: 1946 | F18: =_xlfn.XLOOKUP(D18,'Gemini Output'!B:B,'Gemini Output'!C:C,"No Match Yet") -> 12 | G18: =_xlfn.XLOOKUP(D18,'Gemini Output'!B:B,'Gemini Output'!E:E,"No Match Yet") -> L1 | J18: 9 | K18: History & Religion | L18: Chronological (Timeline, cultural impact) | R18: 9 | S18: =COUNTIF(F:F,R18) -> 118
C19: 16 | D19: por | E19: 1899 | F19: =_xlfn.XLOOKUP(D19,'Gemini Output'!B:B,'Gemini Output'!C:C,"No Match Yet") -> 8 | G19: =_xlfn.XLOOKUP(D19,'Gemini Output'!B:B,'Gemini Output'!E:E,"No Match Yet") -> L1 | J19: 10 | K19: Environment & Nature | L19: Descriptive (Locations, ecological impact) | R19: 10 | S19: =COUNTIF(F:F,R19) -> 59
C20: 17 | D20: para | E20: 1498 | F20: =_xlfn.XLOOKUP(D20,'Gemini Output'!B:B,'Gemini Output'!C:C,"No Match Yet") -> 5 | G20: =_xlfn.XLOOKUP(D20,'Gemini Output'!B:B,'Gemini Output'!E:E,"No Match Yet") -> L1 | J20: 11 | K20: Health & Wellness | L20: Practical (Body parts, medical advice) | R20: 11 | S20: =COUNTIF(F:F,R20) -> 23
C21: 18 | D21: es | E21: 1206 | F21: =_xlfn.XLOOKUP(D21,'Gemini Output'!B:B,'Gemini Output'!C:C,"No Match Yet") -> 1 | G21: =_xlfn.XLOOKUP(D21,'Gemini Output'!B:B,'Gemini Output'!E:E,"No Match Yet") -> L1 | J21: 12 | K21: Social Issues/Society | L21: Sociological (Social groups, demographic trends) | R21: 12 | S21: =COUNTIF(F:F,R21) -> 169
C22: 19 | D22: El | E22: 1182 | F22: =_xlfn.XLOOKUP(D22,'Gemini Output'!B:B,'Gemini Output'!C:C,"No Match Yet") -> 12 | G22: =_xlfn.XLOOKUP(D22,'Gemini Output'!B:B,'Gemini Output'!E:E,"No Match Yet") -> L1 | J22: 13 | K22: Lifestyle & Travel | L22: Experiential (Destination names, habits) | R22: 13 | S22: =COUNTIF(F:F,R22) -> 83
C23: 20 | D23: como | E23: 1140 | F23: =_xlfn.XLOOKUP(D23,'Gemini Output'!B:B,'Gemini Output'!C:C,"No Match Yet") -> 12 | G23: =_xlfn.XLOOKUP(D23,'Gemini Output'!B:B,'Gemini Output'!E:E,"No Match Yet") -> L1 | J23: 14 | K23: Weather & Disaster | L23: Event-driven (Severity, location, response) | R23: 14 | S23: =COUNTIF(F:F,R23) -> 14
C24: 21 | D24: al | E24: 1055 | F24: =_xlfn.XLOOKUP(D24,'Gemini Output'!B:B,'Gemini Output'!C:C,"No Match Yet") -> 13 | G24: =_xlfn.XLOOKUP(D24,'Gemini Output'!B:B,'Gemini Output'!E:E,"No Match Yet") -> L1 | R24: 15 | S24: =COUNTIF(F:F,R24) -> 48
C25: 22 | D25: En | E25: 999 | F25: =_xlfn.XLOOKUP(D25,'Gemini Output'!B:B,'Gemini Output'!C:C,"No Match Yet") -> 10 | G25: =_xlfn.XLOOKUP(D25,'Gemini Output'!B:B,'Gemini Output'!E:E,"No Match Yet") -> L1
C26: 23 | D26: fue | E26: 944 | F26: =_xlfn.XLOOKUP(D26,'Gemini Output'!B:B,'Gemini Output'!C:C,"No Match Yet") -> 9 | G26: =_xlfn.XLOOKUP(D26,'Gemini Output'!B:B,'Gemini Output'!E:E,"No Match Yet") -> L1
C27: 24 | D27: no | E27: 891 | F27: =_xlfn.XLOOKUP(D27,'Gemini Output'!B:B,'Gemini Output'!C:C,"No Match Yet") -> 12 | G27: =_xlfn.XLOOKUP(D27,'Gemini Output'!B:B,'Gemini Output'!E:E,"No Match Yet") -> L1 | J27: Level ID | K27: Logic for AI | L27: Examples from your List
C28: 25 | D28: La | E28: 879 | F28: =_xlfn.XLOOKUP(D28,'Gemini Output'!B:B,'Gemini Output'!C:C,"No Match Yet") -> 12 | G28: =_xlfn.XLOOKUP(D28,'Gemini Output'!B:B,'Gemini Output'!E:E,"No Match Yet") -> L1 | J28: Basic L1 | K28: Common daily vocabulary and basic verbs. | L28: de, la, casa, ciudad, vida, agua, madre, padre, niños, calle, sol, día +4
C29: 26 | D29: más | E29: 855 | F29: =_xlfn.XLOOKUP(D29,'Gemini Output'!B:B,'Gemini Output'!C:C,"No Match Yet") -> 2 | G29: =_xlfn.XLOOKUP(D29,'Gemini Output'!B:B,'Gemini Output'!E:E,"No Match Yet") -> L1 | J29: Intermediate L2 | K29: Subject-specific nouns and active descriptive terms. | L29: equipo, película, música, teatro, fútbol, empresa, historia, naturaleza, viaje, hotel +4
C30: 27 | D30: sus | E30: 663 | F30: =_xlfn.XLOOKUP(D30,'Gemini Output'!B:B,'Gemini Output'!C:C,"No Match Yet") -> 12 | G30: =_xlfn.XLOOKUP(D30,'Gemini Output'!B:B,'Gemini Output'!E:E,"No Match Yet") -> L1 | J30: Advanced L3 | K30: Abstract concepts, technical terminology, and formal administration. | L30: administración, gestión, república, inversión, economía, técnica, infraestructura, legislación +3
C31: 28 | D31: lo | E31: 652 | F31: =_xlfn.XLOOKUP(D31,'Gemini Output'!B:B,'Gemini Output'!C:C,"No Match Yet") -> 15 | G31: =_xlfn.XLOOKUP(D31,'Gemini Output'!B:B,'Gemini Output'!E:E,"No Match Yet") -> L1
C32: 29 | D32: o | E32: 458 | F32: =_xlfn.XLOOKUP(D32,'Gemini Output'!B:B,'Gemini Output'!C:C,"No Match Yet") -> 2 | G32: =_xlfn.XLOOKUP(D32,'Gemini Output'!B:B,'Gemini Output'!E:E,"No Match Yet") -> L1
C33: 30 | D33: también | E33: 390 | F33: =_xlfn.XLOOKUP(D33,'Gemini Output'!B:B,'Gemini Output'!C:C,"No Match Yet") -> 12 | G33: =_xlfn.XLOOKUP(D33,'Gemini Output'!B:B,'Gemini Output'!E:E,"No Match Yet") -> L1
C34: 31 | D34: dos | E34: 379 | F34: =_xlfn.XLOOKUP(D34,'Gemini Output'!B:B,'Gemini Output'!C:C,"No Match Yet") -> 4 | G34: =_xlfn.XLOOKUP(D34,'Gemini Output'!B:B,'Gemini Output'!E:E,"No Match Yet") -> L1
C35: 32 | D35: Los | E35: 377 | F35: =_xlfn.XLOOKUP(D35,'Gemini Output'!B:B,'Gemini Output'!C:C,"No Match Yet") -> 12 | G35: =_xlfn.XLOOKUP(D35,'Gemini Output'!B:B,'Gemini Output'!E:E,"No Match Yet") -> L1
C36: 33 | D36: entre | E36: 373 | F36: =_xlfn.XLOOKUP(D36,'Gemini Output'!B:B,'Gemini Output'!C:C,"No Match Yet") -> 12 | G36: =_xlfn.XLOOKUP(D36,'Gemini Output'!B:B,'Gemini Output'!E:E,"No Match Yet") -> L2
C37: 34 | D37: años | E37: 362 | F37: =_xlfn.XLOOKUP(D37,'Gemini Output'!B:B,'Gemini Output'!C:C,"No Match Yet") -> 9 | G37: =_xlfn.XLOOKUP(D37,'Gemini Output'!B:B,'Gemini Output'!E:E,"No Match Yet") -> L1
C38: 35 | D38: pero | E38: 359 | F38: =_xlfn.XLOOKUP(D38,'Gemini Output'!B:B,'Gemini Output'!C:C,"No Match Yet") -> 12 | G38: =_xlfn.XLOOKUP(D38,'Gemini Output'!B:B,'Gemini Output'!E:E,"No Match Yet") -> L1
C39: 36 | D39: ha | E39: 334 | F39: =_xlfn.XLOOKUP(D39,'Gemini Output'!B:B,'Gemini Output'!C:C,"No Match Yet") -> 9 | G39: =_xlfn.XLOOKUP(D39,'Gemini Output'!B:B,'Gemini Output'!E:E,"No Match Yet") -> L3
C40: 37 | D40: este | E40: 330 | F40: =_xlfn.XLOOKUP(D40,'Gemini Output'!B:B,'Gemini Output'!C:C,"No Match Yet") -> 13 | G40: =_xlfn.XLOOKUP(D40,'Gemini Output'!B:B,'Gemini Output'!E:E,"No Match Yet") -> L1
C41: 38 | D41: sobre | E41: 313 | F41: =_xlfn.XLOOKUP(D41,'Gemini Output'!B:B,'Gemini Output'!C:C,"No Match Yet") -> 12 | G41: =_xlfn.XLOOKUP(D41,'Gemini Output'!B:B,'Gemini Output'!E:E,"No Match Yet") -> L2
C42: 39 | D42: le | E42: 311 | F42: =_xlfn.XLOOKUP(D42,'Gemini Output'!B:B,'Gemini Output'!C:C,"No Match Yet") -> 12 | G42: =_xlfn.XLOOKUP(D42,'Gemini Output'!B:B,'Gemini Output'!E:E,"No Match Yet") -> L1
... C63: 60 | D63: muy | E63: 205 | F63: =_xlfn.XLOOKUP(D63,'Gemini Output'!B:B,'Gemini Output'!C:C,"No Match Yet") -> 14 | G63: =_xlfn.XLOOKUP(D63,'Gemini Output'!B:B,'Gemini Output'!E:E,"No Match Yet") -> L1
C64: 61 | D64: había | E64: 203 | F64: =_xlfn.XLOOKUP(D64,'Gemini Output'!B:B,'Gemini Output'!C:C,"No Match Yet") -> 9 | G64: =_xlfn.XLOOKUP(D64,'Gemini Output'!B:B,'Gemini Output'!E:E,"No Match Yet") -> L1 | K64: The Enhanced "CAT & LEVEL ID" Classifier Prompt
C65: 62 | D65: está | E65: 199 | F65: =_xlfn.XLOOKUP(D65,'Gemini Output'!B:B,'Gemini Output'!C:C,"No Match Yet") -> 11 | G65: =_xlfn.XLOOKUP(D65,'Gemini Output'!B:B,'Gemini Output'!E:E,"No Match Yet") -> L1
C66: 63 | D66: vez | E66: 197 | F66: =_xlfn.XLOOKUP(D66,'Gemini Output'!B:B,'Gemini Output'!C:C,"No Match Yet") -> 9 | G66: =_xlfn.XLOOKUP(D66,'Gemini Output'!B:B,'Gemini Output'!E:E,"No Match Yet") -> L1 | K66: System Role: You are a linguistic data analyst specializing in Spanish morphology, contextual categorization, and CEFR-aligned vocabulary leveling. Your task is to map Spanish words to specific "CAT ID" subjects and "Level IDs" based on their vibe, professional usage, and linguistic complexity.
C67: 64 | D67: primera | E67: 191 | F67: =_xlfn.XLOOKUP(D67,'Gemini Output'!B:B,'Gemini Output'!C:C,"No Match Yet") -> 4 | G67: =_xlfn.XLOOKUP(D67,'Gemini Output'!B:B,'Gemini Output'!E:E,"No Match Yet") -> L1
C68: 65 | D68: mismo | E68: 188 | F68: =_xlfn.XLOOKUP(D68,'Gemini Output'!B:B,'Gemini Output'!C:C,"No Match Yet") -> 12 | G68: =_xlfn.XLOOKUP(D68,'Gemini Output'!B:B,'Gemini Output'!E:E,"No Match Yet") -> L1
C69: 66 | D69: fueron | E69: 183 | F69: =_xlfn.XLOOKUP(D69,'Gemini Output'!B:B,'Gemini Output'!C:C,"No Match Yet") -> 9 | G69: =_xlfn.XLOOKUP(D69,'Gemini Output'!B:B,'Gemini Output'!E:E,"No Match Yet") -> L1
C70: 67 | D70: tiempo | E70: 183 | F70: =_xlfn.XLOOKUP(D70,'Gemini Output'!B:B,'Gemini Output'!C:C,"No Match Yet") -> 9 | G70: =_xlfn.XLOOKUP(D70,'Gemini Output'!B:B,'Gemini Output'!E:E,"No Match Yet") -> L1 | K70: CAT ID Reference Table:
C71: 68 | D71: sido | E71: 176 | F71: =_xlfn.XLOOKUP(D71,'Gemini Output'!B:B,'Gemini Output'!C:C,"No Match Yet") -> 13 | G71: =_xlfn.XLOOKUP(D71,'Gemini Output'!B:B,'Gemini Output'!E:E,"No Match Yet") -> L1
C72: 69 | D72: otros | E72: 175 | F72: =_xlfn.XLOOKUP(D72,'Gemini Output'!B:B,'Gemini Output'!C:C,"No Match Yet") -> 12 | G72: =_xlfn.XLOOKUP(D72,'Gemini Output'!B:B,'Gemini Output'!E:E,"No Match Yet") -> L1 | K72: | ID | Category | Vibe |
C73: 70 | D73: ciudad | E73: 171 | F73: =_xlfn.XLOOKUP(D73,'Gemini Output'!B:B,'Gemini Output'!C:C,"No Match Yet") -> 10 | G73: =_xlfn.XLOOKUP(D73,'Gemini Output'!B:B,'Gemini Output'!E:E,"No Match Yet") -> L1
C74: 71 | D74: embargo | E74: 171 | F74: =_xlfn.XLOOKUP(D74,'Gemini Output'!B:B,'Gemini Output'!C:C,"No Match Yet") -> 2 | G74: =_xlfn.XLOOKUP(D74,'Gemini Output'!B:B,'Gemini Output'!E:E,"No Match Yet") -> L2 | K74: |:---|:---|:---|
C75: 72 | D75: uno | E75: 171 | F75: =_xlfn.XLOOKUP(D75,'Gemini Output'!B:B,'Gemini Output'!C:C,"No Match Yet") -> 4 | G75: =_xlfn.XLOOKUP(D75,'Gemini Output'!B:B,'Gemini Output'!E:E,"No Match Yet") -> L1
C76: 73 | D76: todo | E76: 170 | F76: =_xlfn.XLOOKUP(D76,'Gemini Output'!B:B,'Gemini Output'!C:C,"No Match Yet") -> 12 | G76: =_xlfn.XLOOKUP(D76,'Gemini Output'!B:B,'Gemini Output'!E:E,"No Match Yet") -> L1 | K76: | 1 | Politics & Government | Fact-based (Laws, years) |
C77: 74 | D77: primer | E77: 168 | F77: =_xlfn.XLOOKUP(D77,'Gemini Output'!B:B,'Gemini Output'!C:C,"No Match Yet") -> 7 | G77: =_xlfn.XLOOKUP(D77,'Gemini Output'!B:B,'Gemini Output'!E:E,"No Match Yet") -> L1
C78: 75 | D78: solo | E78: 165 | F78: =_xlfn.XLOOKUP(D78,'Gemini Output'!B:B,'Gemini Output'!C:C,"No Match Yet") -> 13 | G78: =_xlfn.XLOOKUP(D78,'Gemini Output'!B:B,'Gemini Output'!E:E,"No Match Yet") -> L1 | K78: | 2 | Economy & Finance | Logical/Numerical (Trends, growth) |
C79: 76 | D79: cada | E79: 162 | F79: =_xlfn.XLOOKUP(D79,'Gemini Output'!B:B,'Gemini Output'!C:C,"No Match Yet") -> 5 | G79: =_xlfn.XLOOKUP(D79,'Gemini Output'!B:B,'Gemini Output'!E:E,"No Match Yet") -> L1
C80: 77 | D80: lugar | E80: 161 | F80: =_xlfn.XLOOKUP(D80,'Gemini Output'!B:B,'Gemini Output'!C:C,"No Match Yet") -> 13 | G80: =_xlfn.XLOOKUP(D80,'Gemini Output'!B:B,'Gemini Output'!E:E,"No Match Yet") -> L1 | K80: | 3 | Arts & Entertainment | Creative/Recall (Names, works) |
C81: 78 | D81: gran | E81: 160 | F81: =_xlfn.XLOOKUP(D81,'Gemini Output'!B:B,'Gemini Output'!C:C,"No Match Yet") -> 3 | G81: =_xlfn.XLOOKUP(D81,'Gemini Output'!B:B,'Gemini Output'!E:E,"No Match Yet") -> L1
C82: 79 | D82: tres | E82: 160 | F82: =_xlfn.XLOOKUP(D82,'Gemini Output'!B:B,'Gemini Output'!C:C,"No Match Yet") -> 2 | G82: =_xlfn.XLOOKUP(D82,'Gemini Output'!B:B,'Gemini Output'!E:E,"No Match Yet") -> L1 | K82: | 4 | Sports | Statistic/Outcome (Scores, teams) |
C83: 80 | D83: forma | E83: 153 | F83: =_xlfn.XLOOKUP(D83,'Gemini Output'!B:B,'Gemini Output'!C:C,"No Match Yet") -> 6 | G83: =_xlfn.XLOOKUP(D83,'Gemini Output'!B:B,'Gemini Output'!E:E,"No Match Yet") -> L1
C84: 81 | D84: nombre | E84: 150 | F84: =_xlfn.XLOOKUP(D84,'Gemini Output'!B:B,'Gemini Output'!C:C,"No Match Yet") -> 3 | G84: =_xlfn.XLOOKUP(D84,'Gemini Output'!B:B,'Gemini Output'!E:E,"No Match Yet") -> L1 | K84: | 5 | Business & Labor | Operational (Hiring, trade) |
C85: 82 | D85: Por | E85: 149 | F85: =_xlfn.XLOOKUP(D85,'Gemini Output'!B:B,'Gemini Output'!C:C,"No Match Yet") -> 8 | G85: =_xlfn.XLOOKUP(D85,'Gemini Output'!B:B,'Gemini Output'!E:E,"No Match Yet") -> L1
C86: 83 | D86: e | E86: 147 | F86: =_xlfn.XLOOKUP(D86,'Gemini Output'!B:B,'Gemini Output'!C:C,"No Match Yet") -> 12 | G86: =_xlfn.XLOOKUP(D86,'Gemini Output'!B:B,'Gemini Output'!E:E,"No Match Yet") -> L1 | K86: | 6 | Science & Tech | Conceptual (Discovery, how-to) |
C87: 84 | D87: Es | E87: 144 | F87: =_xlfn.XLOOKUP(D87,'Gemini Output'!B:B,'Gemini Output'!C:C,"No Match Yet") -> 1 | G87: =_xlfn.XLOOKUP(D87,'Gemini Output'!B:B,'Gemini Output'!E:E,"No Match Yet") -> L1
C88: 85 | D88: Sin | E88: 142 | F88: =_xlfn.XLOOKUP(D88,'Gemini Output'!B:B,'Gemini Output'!C:C,"No Match Yet") -> 8 | G88: =_xlfn.XLOOKUP(D88,'Gemini Output'!B:B,'Gemini Output'!E:E,"No Match Yet") -> L1 | K88: | 7 | Education | Institutional (Degrees, research) |
C89: 86 | D89: mayor | E89: 140 | F89: =_xlfn.XLOOKUP(D89,'Gemini Output'!B:B,'Gemini Output'!C:C,"No Match Yet") -> 2 | G89: =_xlfn.XLOOKUP(D89,'Gemini Output'!B:B,'Gemini Output'!E:E,"No Match Yet") -> L2
C90: 87 | D90: tanto | E90: 137 | F90: =_xlfn.XLOOKUP(D90,'Gemini Output'!B:B,'Gemini Output'!C:C,"No Match Yet") -> 4 | G90: =_xlfn.XLOOKUP(D90,'Gemini Output'!B:B,'Gemini Output'!E:E,"No Match Yet") -> L2 | K90: | 8 | Crime, Law & Justice | Narrative (Rulings, events) |
C91: 88 | D91: todos | E91: 137 | F91: =_xlfn.XLOOKUP(D91,'Gemini Output'!B:B,'Gemini Output'!C:C,"No Match Yet") -> 12 | G91: =_xlfn.XLOOKUP(D91,'Gemini Output'!B:B,'Gemini Output'!E:E,"No Match Yet") -> L1
C92: 89 | D92: pueden | E92: 136 | F92: =_xlfn.XLOOKUP(D92,'Gemini Output'!B:B,'Gemini Output'!C:C,"No Match Yet") -> 6 | G92: =_xlfn.XLOOKUP(D92,'Gemini Output'!B:B,'Gemini Output'!E:E,"No Match Yet") -> L1 | K92: | 9 | History & Religion | Chronological (Timelines, eras) |
C93: 90 | D93: vida | E93: 135 | F93: =_xlfn.XLOOKUP(D93,'Gemini Output'!B:B,'Gemini Output'!C:C,"No Match Yet") -> 11 | G93: =_xlfn.XLOOKUP(D93,'Gemini Output'!B:B,'Gemini Output'!E:E,"No Match Yet") -> L1
C94: 91 | D94: Al | E94: 134 | F94: =_xlfn.XLOOKUP(D94,'Gemini Output'!B:B,'Gemini Output'!C:C,"No Match Yet") -> 13 | G94: =_xlfn.XLOOKUP(D94,'Gemini Output'!B:B,'Gemini Output'!E:E,"No Match Yet") -> L1 | K94: | 10 | Environment & Nature | Descriptive (Locations, ecology) |
C95: 92 | D95: han | E95: 134 | F95: =_xlfn.XLOOKUP(D95,'Gemini Output'!B:B,'Gemini Output'!C:C,"No Match Yet") -> 9 | G95: =_xlfn.XLOOKUP(D95,'Gemini Output'!B:B,'Gemini Output'!E:E,"No Match Yet") -> L1
C96: 93 | D96: mientras | E96: 134 | F96: =_xlfn.XLOOKUP(D96,'Gemini Output'!B:B,'Gemini Output'!C:C,"No Match Yet") -> 9 | G96: =_xlfn.XLOOKUP(D96,'Gemini Output'!B:B,'Gemini Output'!E:E,"No Match Yet") -> L2 | K96: | 11 | Health & Wellness | Practical (Medical, body) |
C97: 94 | D97: él | E97: 134 | F97: =_xlfn.XLOOKUP(D97,'Gemini Output'!B:B,'Gemini Output'!C:C,"No Match Yet") -> 15 | G97: =_xlfn.XLOOKUP(D97,'Gemini Output'!B:B,'Gemini Output'!E:E,"No Match Yet") -> L1
C98: 95 | D98: así | E98: 133 | F98: =_xlfn.XLOOKUP(D98,'Gemini Output'!B:B,'Gemini Output'!C:C,"No Match Yet") -> 8 | G98: =_xlfn.XLOOKUP(D98,'Gemini Output'!B:B,'Gemini Output'!E:E,"No Match Yet") -> L1 | K98: | 12 | Social Issues/Society | Sociological (Demographics, groups) |
C99: 96 | D99: Fue | E99: 132 | F99: =_xlfn.XLOOKUP(D99,'Gemini Output'!B:B,'Gemini Output'!C:C,"No Match Yet") -> 9 | G99: =_xlfn.XLOOKUP(D99,'Gemini Output'!B:B,'Gemini Output'!E:E,"No Match Yet") -> L1
C100: 97 | D100: nuevo | E100: 132 | F100: =_xlfn.XLOOKUP(D100,'Gemini Output'!B:B,'Gemini Output'!C:C,"No Match Yet") -> 6 | G100: =_xlfn.XLOOKUP(D100,'Gemini Output'!B:B,'Gemini Output'!E:E,"No Match Yet") -> L1 | K100: | 13 | Lifestyle & Travel | Experiential (Destinations, habits) |
C101: 98 | D101: si | E101: 131 | F101: =_xlfn.XLOOKUP(D101,'Gemini Output'!B:B,'Gemini Output'!C:C,"No Match Yet") -> 8 | G101: =_xlfn.XLOOKUP(D101,'Gemini Output'!B:B,'Gemini Output'!E:E,"No Match Yet") -> L1
C102: 99 | D102: grupo | E102: 127 | F102: =_xlfn.XLOOKUP(D102,'Gemini Output'!B:B,'Gemini Output'!C:C,"No Match Yet") -> 5 | G102: =_xlfn.XLOOKUP(D102,'Gemini Output'!B:B,'Gemini Output'!E:E,"No Match Yet") -> L2 | K102: | 14 | Weather & Disaster | Event-driven (Severity, response) |
C103: 100 | D103: También | E103: 126 | F103: =_xlfn.XLOOKUP(D103,'Gemini Output'!B:B,'Gemini Output'!C:C,"No Match Yet") -> 12 | G103: =_xlfn.XLOOKUP(D103,'Gemini Output'!B:B,'Gemini Output'!E:E,"No Match Yet") -> L1
C104: 101 | D104: día | E104: 125 | F104: =_xlfn.XLOOKUP(D104,'Gemini Output'!B:B,'Gemini Output'!C:C,"No Match Yet") -> 13 | G104: =_xlfn.XLOOKUP(D104,'Gemini Output'!B:B,'Gemini Output'!E:E,"No Match Yet") -> L1 | K104: | 15 | Misc. Does not fit into other categories |
C105: 102 | D105: contra | E105: 124 | F105: =_xlfn.XLOOKUP(D105,'Gemini Output'!B:B,'Gemini Output'!C:C,"No Match Yet") -> 8 | G105: =_xlfn.XLOOKUP(D105,'Gemini Output'!B:B,'Gemini Output'!E:E,"No Match Yet") -> L1
C106: 103 | D106: otras | E106: 123 | F106: =_xlfn.XLOOKUP(D106,'Gemini Output'!B:B,'Gemini Output'!C:C,"No Match Yet") -> 12 | G106: =_xlfn.XLOOKUP(D106,'Gemini Output'!B:B,'Gemini Output'!E:E,"No Match Yet") -> L1
C107: 104 | D107: ese | E107: 122 | F107: =_xlfn.XLOOKUP(D107,'Gemini Output'!B:B,'Gemini Output'!C:C,"No Match Yet") -> 13 | G107: =_xlfn.XLOOKUP(D107,'Gemini Output'!B:B,'Gemini Output'!E:E,"No Match Yet") -> L1
C108: 105 | D108: De | E108: 121 | F108: =_xlfn.XLOOKUP(D108,'Gemini Output'!B:B,'Gemini Output'!C:C,"No Match Yet") -> 1 | G108: =_xlfn.XLOOKUP(D108,'Gemini Output'!B:B,'Gemini Output'!E:E,"No Match Yet") -> L1 | K108: Level ID Reference Table:
C109: 106 | D109: antes | E109: 120 | F109: =_xlfn.XLOOKUP(D109,'Gemini Output'!B:B,'Gemini Output'!C:C,"No Match Yet") -> 9 | G109: =_xlfn.XLOOKUP(D109,'Gemini Output'!B:B,'Gemini Output'!E:E,"No Match Yet") -> L1
C110: 107 | D110: ella | E110: 120 | F110: =_xlfn.XLOOKUP(D110,'Gemini Output'!B:B,'Gemini Output'!C:C,"No Match Yet") -> 12 | G110: =_xlfn.XLOOKUP(D110,'Gemini Output'!B:B,'Gemini Output'!E:E,"No Match Yet") -> L1 | K110: | Level | Logic for AI | Examples |
C111: 108 | D111: Esta | E111: 119 | F111: =_xlfn.XLOOKUP(D111,'Gemini Output'!B:B,'Gemini Output'!C:C,"No Match Yet") -> 13 | G111: =_xlfn.XLOOKUP(D111,'Gemini Output'!B:B,'Gemini Output'!E:E,"No Match Yet") -> L1
C112: 109 | D112: Este | E112: 117 | F112: =_xlfn.XLOOKUP(D112,'Gemini Output'!B:B,'Gemini Output'!C:C,"No Match Yet") -> 13 | G112: =_xlfn.XLOOKUP(D112,'Gemini Output'!B:B,'Gemini Output'!E:E,"No Match Yet") -> L1 | K112: |:---|:---|:---|
C113: 110 | D113: cual | E113: 117 | F113: =_xlfn.XLOOKUP(D113,'Gemini Output'!B:B,'Gemini Output'!C:C,"No Match Yet") -> 7 | G113: =_xlfn.XLOOKUP(D113,'Gemini Output'!B:B,'Gemini Output'!E:E,"No Match Yet") -> L2
C114: 111 | D114: personas | E114: 115 | F114: =_xlfn.XLOOKUP(D114,'Gemini Output'!B:B,'Gemini Output'!C:C,"No Match Yet") -> 12 | G114: =_xlfn.XLOOKUP(D114,'Gemini Output'!B:B,'Gemini Output'!E:E,"No Match Yet") -> L1 | K114: | L1 (Basic) | Common daily vocabulary, high-frequency particles, and basic verbs. | de, casa, vida, niños, sol |
C115: 112 | D115: trabajo | E115: 115 | F115: =_xlfn.XLOOKUP(D115,'Gemini Output'!B:B,'Gemini Output'!C:C,"No Match Yet") -> 5 | G115: =_xlfn.XLOOKUP(D115,'Gemini Output'!B:B,'Gemini Output'!E:E,"No Match Yet") -> L1
C116: 113 | D116: Una | E116: 114 | F116: =_xlfn.XLOOKUP(D116,'Gemini Output'!B:B,'Gemini Output'!C:C,"No Match Yet") -> 12 | G116: =_xlfn.XLOOKUP(D116,'Gemini Output'!B:B,'Gemini Output'!E:E,"No Match Yet") -> L1 | K116: | L2 (Intermediate) | Subject-specific nouns and active descriptive terms used in general media. | equipo, película, historia, viaje |
C117: 114 | D117: estaba | E117: 111 | F117: =_xlfn.XLOOKUP(D117,'Gemini Output'!B:B,'Gemini Output'!C:C,"No Match Yet") -> 13 | G117: =_xlfn.XLOOKUP(D117,'Gemini Output'!B:B,'Gemini Output'!E:E,"No Match Yet") -> L1
C118: 115 | D118: Después | E118: 110 | F118: =_xlfn.XLOOKUP(D118,'Gemini Output'!B:B,'Gemini Output'!C:C,"No Match Yet") -> 9 | G118: =_xlfn.XLOOKUP(D118,'Gemini Output'!B:B,'Gemini Output'!E:E,"No Match Yet") -> L1 | K118: | L3 (Advanced) | Abstract concepts, technical terminology, and formal administration/jargon. | gestión, infraestructura, legislación |
C119: 116 | D119: serie | E119: 109 | F119: =_xlfn.XLOOKUP(D119,'Gemini Output'!B:B,'Gemini Output'!C:C,"No Match Yet") -> 3 | G119: =_xlfn.XLOOKUP(D119,'Gemini Output'!B:B,'Gemini Output'!E:E,"No Match Yet") -> L2
C120: 117 | D120: aunque | E120: 107 | F120: =_xlfn.XLOOKUP(D120,'Gemini Output'!B:B,'Gemini Output'!C:C,"No Match Yet") -> 12 | G120: =_xlfn.XLOOKUP(D120,'Gemini Output'!B:B,'Gemini Output'!E:E,"No Match Yet") -> L2
C121: 118 | D121: mundo | E121: 107 | F121: =_xlfn.XLOOKUP(D121,'Gemini Output'!B:B,'Gemini Output'!C:C,"No Match Yet") -> 10 | G121: =_xlfn.XLOOKUP(D121,'Gemini Output'!B:B,'Gemini Output'!E:E,"No Match Yet") -> L1
C122: 119 | D122: bajo | E122: 106 | F122: =_xlfn.XLOOKUP(D122,'Gemini Output'!B:B,'Gemini Output'!C:C,"No Match Yet") -> 8 | G122: =_xlfn.XLOOKUP(D122,'Gemini Output'!B:B,'Gemini Output'!E:E,"No Match Yet") -> L1 | K122: Instructions:
...

Sheet Gemini Output
B1: Word | C1: CAT ID | D1: Category Name | E1: Level | F1: Reasoning
B2: También | C2: 12 | D2: Social Issues/Society | E2: L1 | F2: High-frequency additive conjunction used in all contexts.
B3: día | C3: 13 | D3: Lifestyle & Travel | E3: L1 | F3: Fundamental temporal noun for daily life.
B4: contra | C4: 8 | D4: Crime, Law & Justice | E4: L1 | F4: High-frequency preposition; often used for opposition or legal cases.
B5: otras | C5: 12 | D5: Social Issues/Society | E5: L1 | F5: Basic determiner for distinguishing groups or things.
B6: ese | C6: 13 | D6: Lifestyle & Travel | E6: L1 | F6: Common demonstrative pronoun used in everyday speech.
B7: De | C7: 1 | D7: Politics & Government | E7: L1 | F7: Universal preposition; essential for possession and origin.
B8: antes | C8: 9 | D8: History & Religion | E8: L1 | F8: Basic temporal marker used to establish timelines.
B9: ella | C9: 12 | D9: Social Issues/Society | E9: L1 | F9: High-frequency personal pronoun.
B10: Esta | C10: 13 | D10: Lifestyle & Travel | E10: L1 | F10: Common feminine demonstrative pronoun.
B11: Este | C11: 13 | D11: Lifestyle & Travel | E11: L1 | F11: Common masculine demonstrative pronoun.
B12: cual | C12: 7 | D12: Education | E12: L2 | F12: Relative pronoun used in more structured, formal explanations.
B13: personas | C13: 12 | D13: Social Issues/Society | E13: L1 | F13: Fundamental noun for human beings.
... B52: largo | C52: 10 | D52: Environment & Nature | E52: L1 | F52: Basic descriptive adjective for length.
B53: había | C53: 9 | E53: L1
B54: está | C54: 11 | E54: L1
B55: vez | C55: 9 | E55: L1
B56: primera | C56: 4 | E56: L1
B57: mismo | C57: 12 | E57: L1
B58: fueron | C58: 9 | E58: L1
B59: tiempo | C59: 9 | E59: L1
B60: sido | C60: 13 | E60: L1
B61: otros | C61: 12 | E61: L1
B62: ciudad | C62: 10 | E62: L1
B63: embargo | C63: 2 | E63: L2
B64: uno | C64: 4 | E64: L1
... B72: forma | C72: 6 | E72: L1
B73: Japón | C73: 13 | D73: Lifestyle & Travel | E73: L1 | F73: Common proper noun for a destination; basic geographical knowledge.
B74: Jesús | C74: 9 | D74: History & Religion | E74: L1 | F74: Central figure in religious chronology and high-frequency proper name.
B75: Posteriormente | C75: 9 | D75: History & Religion | E75: L3 | F75: Formal transition word used to establish chronological order in narratives.
B76: Unido | C76: 1 | D76: Politics & Government | E76: L2 | F76: Often used in political contexts (Reino Unido, Estados Unidos) or formal alliances.
B77: Ya | C77: 15 | D77: Misc. | E77: L1 | F77: High-frequency temporal particle; functional daily vocabulary.
B78: bases | C78: 6 | D78: Science & Tech | E78: L2 | F78: Conceptual term referring to foundations or fundamental principles of a system.
B79: curso | C79: 7 | D79: Education | E79: L2 | F79: Subject-specific noun referring to a period of study or institutional timeline.
B80: detrás | C80: 10 | D80: Environment & Nature | E80: L1 | F80: Basic spatial preposition used to describe locations.
B81: dicha | C81: 8 | D81: Crime, Law & Justice | E81: L3 | F81: Formal/archaic referential term common in legal narrative and rulings.
B82: económica | C82: 2 | D82: Economy & Finance | E82: L2 | F82: Adjective describing logical/numerical trends and financial systems.
B83: edificios | C83: 10 | D83: Environment & Nature | E83: L2 | F83: Descriptive noun for physical locations and urban ecology.
B84: eje | C84: 6 | D84: Science & Tech | E84: L3 | F84: Abstract/technical term for a central line or conceptual pivot point.
... B166: velocidad | C166: 6 | D166: Science & Tech | E166: L2 | F166: Conceptual/Technical term describing a measurable physical property.
B167: 1988 | C167: 9 | D167: History & Religion | E167: L1 | F167: Chronological marker defining a specific year in a timeline.
B168: 1990 | C168: 9 | D168: History & Religion | E168: L1 | F168: Chronological marker defining a specific year in a timeline.
B169: 1997 | C169: 9 | D169: History & Religion | E169: L1 | F169: Chronological marker defining a specific year in a timeline.
B170: 40 | C170: 2 | D170: Economy & Finance | E170: L1 | F170: Basic numerical data used for trends, growth, or accounting.
B171: Antonio | C171: 3 | D171: Arts & Entertainment | E171: L1 | F171: Common proper name with high cultural recall value.
B172: Está | C172: 11 | D172: Health & Wellness | E172: L1 | F172: Basic verb describing practical states of being or physical health.
B173: Gran | C173: 3 | D173: Arts & Entertainment | E173: L1 | F173: Adjective used to describe significant creative works or names.
B174: Mundial | C174: 4 | D174: Sports | E174: L2 | F174: High-frequency term in sports context (World Cup/Championships) referring to global outcomes.
B175: Reino | C175: 1 | D175: Politics & Government | E175: L2 | F175: Fact-based term for a type of state or sovereignty (Kingdom).
B176: XIX | C176: 9 | D176: History & Religion | E176: L2 | F176: Roman numerals used almost exclusively for chronological centuries and historical eras.
B177: York | C177: 13 | D177: Lifestyle & Travel | E177: L1 | F177: Proper noun used for a major destination (New York).
B178: actualmente | C178: 1 | D178: Politics & Government | E178: L2 | F178: Temporal marker used to describe the current state of laws or government affairs.
B179: aguas | C179: 10 | D179: Environment & Nature | E179: L1 | F179: Basic descriptive noun for ecological and natural resources.
B180: antigua | C180: 9 | D180: History & Religion | E180: L2 | F180: Adjective used to describe chronological timelines and historical periods.
B181: artículos | C181: 1 | D181: Politics & Government | E181: L3 | F181: Technical term for sections of laws, treaties, or constitutional facts.
B182: barrio | C182: 12 | D182: Social Issues/Society | E182: L2 | F182: Sociological term for urban demographics and community groups.
... B541: trabajar | C541: 5 | D541: Business & Labor | E541: L1 | F541: Operational; the core verb for labor and hiring.
B542: 22 | C542: 1 | D542: Politics & Government | E542: L1 | F542: Fact-based; usually refers to a specific law, year, or article number.
B543: Algunos | C543: 12 | D543: Social Issues/Society | E543: L1 | F543: Sociological; refers to a subset of a population.
B544: Ciudad | C544: 12 | D544: Social Issues/Society | E544: L1 | F544: Sociological; demographic and population-centered.
B545: Francisco | C545: 9 | D545: History & Religion | E545: L1 | F545: Creative/Recall; often refers to saints, popes, or historical figures.
B546: General | C546: 1 | D546: Politics & Government | E546: L2 | F546: Fact-based; refers to military rank or high-level government titles.
B547: Grupo | C547: 5 | D547: Business & Labor | E547: L2 | F547: Operational; refers to a business conglomerate or work group.
B548: Internacional | C548: 1 | D548: Politics & Government | E548: L2 | F548: Fact-based; refers to foreign relations and treaties.
B549: Premio | C549: 3 | D549: Arts & Entertainment | E549: L2 | F549: Creative/Recall; synonymous with artistic accolades.
B550: República | C550: 1 | D550: Politics & Government | E550: L2 | F550: Fact-based; defines a specific form of government.
B551: amigos | C551: 13 | D551: Lifestyle & Travel | E551: L1 | F551: Experiential; social habits and leisure activities.
B552: aquí | C552: 10 | D552: Environment & Nature | E552: L1 | F552: Descriptive; identifies a location or specific ecological spot.
B553: calidad | C553: 5 | D553: Business & Labor | E553: L2 | F553: Operational; refers to quality control in trade and production.
B554: capaz | C554: 7 | D554: Education | E554: L2 | F554: Institutional; refers to student capability or research potential.
... B578: Gobierno | C578: 1 | D578: Politics & Government | E578: L2 | F578: Fact-based; the central entity of laws and governance.
B579: Ha | C579: 9 | D579: History & Religion | E579: L3
B580: II | C580: 9 | D580: History & Religion | E580: L1 | F580: Chronological; used for kings, wars (WWII), or specific eras. | I580: Chronological; auxiliary verb used to build past timelines.
B581: Sur | C581: 10 | D581: Environment & Nature | E581: L1 | F581: Descriptive; geographic direction and location mapping.
B582: Uno | C582: 4 | D582: Sports | E582: L1 | F582: Statistic/Outcome; ranking as #1 or scoring one goal.
B583: administración | C583: 1 | D583: Politics & Government | E583: L3 | F583: Fact-based; refers to a specific presidential or state administration.
B584: aire | C584: 14 | D584: Weather & Disaster | E584: L1 | F584: Event-driven; refers to air quality, wind, and storm severity.
B585: social | C585: 12 | D585: Social Issues/Society | E585: L2 | F585: Directly addresses sociological structures and demographics.
B586: Europa | C586: 10 | D586: Environment & Nature | E586: L1 | F586: Descriptive of a major geographical location and landmass.
B587: Y | C587: 12 | D587: Social Issues/Society | E587: L1 | F587: A coordinator often used to link social groups or demographic categories.
B588: arte | C588: 3 | D588: Arts & Entertainment | E588: L2 | F588: Central term for creative works and artistic expression.
B589: cabo | C589: 8 | D589: Crime, Law & Justice | E589: L2 | F589: Often used in the legal/narrative phrase "llevar a cabo" regarding rulings or events.
B590: efecto | C590: 6 | D590: Science & Tech | E590: L2 | F590: Conceptual; refers to the cause-and-effect results of a discovery or process.
B591: español | C591: 12 | D591: Social Issues/Society | E591: L1 | F591: Sociological; refers to a demographic group or a cultural/linguistic identifier.
B592: gente | C592: 12 | D592: Social Issues/Society | E592: L1 | F592: Refers to people as a sociological or demographic group.
... B974: mujeres | C974: 12 | D974: Social Issues/Society | E974: L1 | F974: Sociological; key demographic group for social and gender issues.

Sheet Cleaning File
A1: WORD ID | B1: word | C1: Frequency | D1: CAT ID | E1: LEVEL ID | I1: WORD ID | J1: word | K1: Frequency | L1: CAT ID | M1: LEVEL ID
A2: 1 | B2: de | C2: 15226 | D2: 1 | E2: L1 | I2: 252 | J2: =_xlfn.XLOOKUP($I2,$A:$A,B:B) -> abril | K2: =_xlfn.XLOOKUP($I2,$A:$A,C:C) -> 63 | L2: =_xlfn.XLOOKUP($I2,$A:$A,D:D) -> 13 | M2: =_xlfn.XLOOKUP($I2,$A:$A,E:E) -> L1
A3: 2 | B3: la | C3: 7493 | D3: 12 | E3: L1 | I3: 896 | J3: =_xlfn.XLOOKUP($I3,$A:$A,B:B) -> Academia | K3: =_xlfn.XLOOKUP($I3,$A:$A,C:C) -> 23 | L3: =_xlfn.XLOOKUP($I3,$A:$A,D:D) -> 7 | M3: =_xlfn.XLOOKUP($I3,$A:$A,E:E) -> L2
A4: 3 | B4: en | C4: 5973 | D4: 10 | E4: L1 | I4: 990 | J4: =_xlfn.XLOOKUP($I4,$A:$A,B:B) -> acceso | K4: =_xlfn.XLOOKUP($I4,$A:$A,C:C) -> 21 | L4: =_xlfn.XLOOKUP($I4,$A:$A,D:D) -> 5 | M4: =_xlfn.XLOOKUP($I4,$A:$A,E:E) -> L2
A5: 4 | B5: el | C5: 5435 | D5: 12 | E5: L1 | I5: 905 | J5: =_xlfn.XLOOKUP($I5,$A:$A,B:B) -> accidente | K5: =_xlfn.XLOOKUP($I5,$A:$A,C:C) -> 22 | L5: =_xlfn.XLOOKUP($I5,$A:$A,D:D) -> 14 | M5: =_xlfn.XLOOKUP($I5,$A:$A,E:E) -> L2
A6: 5 | B6: y | C6: 5422 | D6: 12 | E6: L1 | I6: 486 | J6: =_xlfn.XLOOKUP($I6,$A:$A,B:B) -> acción | K6: =_xlfn.XLOOKUP($I6,$A:$A,C:C) -> 0 | L6: =_xlfn.XLOOKUP($I6,$A:$A,D:D) -> 2 | M6: =_xlfn.XLOOKUP($I6,$A:$A,E:E) -> L2
A7: 6 | B7: que | C7: 4171 | D7: 12 | E7: L1 | I7: 906 | J7: =_xlfn.XLOOKUP($I7,$A:$A,B:B) -> acerca | K7: =_xlfn.XLOOKUP($I7,$A:$A,C:C) -> 22 | L7: =_xlfn.XLOOKUP($I7,$A:$A,D:D) -> 7 | M7: =_xlfn.XLOOKUP($I7,$A:$A,E:E) -> L2
I8: 372 | J8: =_xlfn.XLOOKUP($I8,$A:$A,B:B) -> actividad | K8: =_xlfn.XLOOKUP($I8,$A:$A,C:C) -> 46 | L8: =_xlfn.XLOOKUP($I8,$A:$A,D:D) -> 13 | M8: =_xlfn.XLOOKUP($I8,$A:$A,E:E) -> L2
A9: 8 | B9: se | C9: 2845 | D9: 12 | E9: L1 | I9: 471 | J9: =_xlfn.XLOOKUP($I9,$A:$A,B:B) -> actividades | K9: =_xlfn.XLOOKUP($I9,$A:$A,C:C) -> 38 | L9: =_xlfn.XLOOKUP($I9,$A:$A,D:D) -> 13 | M9: =_xlfn.XLOOKUP($I9,$A:$A,E:E) -> L2
A10: 9 | B10: los | C10: 2800 | D10: 12 | E10: L1 | I10: 855 | J10: =_xlfn.XLOOKUP($I10,$A:$A,B:B) -> acto | K10: =_xlfn.XLOOKUP($I10,$A:$A,C:C) -> 23 | L10: =_xlfn.XLOOKUP($I10,$A:$A,D:D) -> 8 | M10: =_xlfn.XLOOKUP($I10,$A:$A,E:E) -> L2
A11: 10 | B11: del | C11: 2645 | D11: 1 | E11: L1 | I11: 729 | J11: =_xlfn.XLOOKUP($I11,$A:$A,B:B) -> actor | K11: =_xlfn.XLOOKUP($I11,$A:$A,C:C) -> 27 | L11: =_xlfn.XLOOKUP($I11,$A:$A,D:D) -> 3 | M11: =_xlfn.XLOOKUP($I11,$A:$A,E:E) -> L1
A12: 11 | B12: un | C12: 2205 | D12: 12 | E12: L1 | I12: 520 | J12: =_xlfn.XLOOKUP($I12,$A:$A,B:B) -> actual | K12: =_xlfn.XLOOKUP($I12,$A:$A,C:C) -> 35 | L12: =_xlfn.XLOOKUP($I12,$A:$A,D:D) -> 1 | M12: =_xlfn.XLOOKUP($I12,$A:$A,E:E) -> L2
A13: 12 | B13: su | C13: 2051 | D13: 5 | E13: L1 | I13: 441 | J13: =_xlfn.XLOOKUP($I13,$A:$A,B:B) -> actualidad | K13: =_xlfn.XLOOKUP($I13,$A:$A,C:C) -> 40 | L13: =_xlfn.XLOOKUP($I13,$A:$A,D:D) -> 1 | M13: =_xlfn.XLOOKUP($I13,$A:$A,E:E) -> L2
A14: 13 | B14: una | C14: 2023 | D14: 12 | E14: L1 | I14: 468 | J14: =_xlfn.XLOOKUP($I14,$A:$A,B:B) -> Actualmente | K14: =_xlfn.XLOOKUP($I14,$A:$A,C:C) -> 38 | L14: =_xlfn.XLOOKUP($I14,$A:$A,D:D) -> 1 | M14: =_xlfn.XLOOKUP($I14,$A:$A,E:E) -> L2
A15: 14 | B15: con | C15: 2014 | D15: 12 | E15: L1 | I15: 299 | J15: =_xlfn.XLOOKUP($I15,$A:$A,B:B) -> acuerdo | K15: =_xlfn.XLOOKUP($I15,$A:$A,C:C) -> 55 | L15: =_xlfn.XLOOKUP($I15,$A:$A,D:D) -> 1 | M15: =_xlfn.XLOOKUP($I15,$A:$A,E:E) -> L2
A16: 15 | B16: las | C16: 1946 | D16: 12 | E16: L1 | I16: 907 | J16: =_xlfn.XLOOKUP($I16,$A:$A,B:B) -> adelante | K16: =_xlfn.XLOOKUP($I16,$A:$A,C:C) -> 22 | L16: =_xlfn.XLOOKUP($I16,$A:$A,D:D) -> 13 | M16: =_xlfn.XLOOKUP($I16,$A:$A,E:E) -> L1
A17: 16 | B17: por | C17: 1899 | D17: 8 | E17: L1 | I17: 145 | J17: =_xlfn.XLOOKUP($I17,$A:$A,B:B) -> Además | K17: =_xlfn.XLOOKUP($I17,$A:$A,C:C) -> 94 | L17: =_xlfn.XLOOKUP($I17,$A:$A,D:D) -> 12 | M17: =_xlfn.XLOOKUP($I17,$A:$A,E:E) -> L2
A18: 17 | B18: para | C18: 1498 | D18: 5 | E18: L1 | I18: 698 | J18: =_xlfn.XLOOKUP($I18,$A:$A,B:B) -> administración | K18: =_xlfn.XLOOKUP($I18,$A:$A,C:C) -> 28 | L18: =_xlfn.XLOOKUP($I18,$A:$A,D:D) -> 1 | M18: =_xlfn.XLOOKUP($I18,$A:$A,E:E) -> L3
A19: 18 | B19: es | C19: 1206 | D19: 1 | E19: L1 | I19: 249 | J19: =_xlfn.XLOOKUP($I19,$A:$A,B:B) -> agosto | K19: =_xlfn.XLOOKUP($I19,$A:$A,C:C) -> 64 | L19: =_xlfn.XLOOKUP($I19,$A:$A,D:D) -> 13 | M19: =_xlfn.XLOOKUP($I19,$A:$A,E:E) -> L1
I20: 281 | J20: =_xlfn.XLOOKUP($I20,$A:$A,B:B) -> agua | K20: =_xlfn.XLOOKUP($I20,$A:$A,C:C) -> 57 | L20: =_xlfn.XLOOKUP($I20,$A:$A,D:D) -> 10 | M20: =_xlfn.XLOOKUP($I20,$A:$A,E:E) -> L1
A21: 20 | B21: como | C21: 1140 | D21: 12 | E21: L1 | I21: 805 | J21: =_xlfn.XLOOKUP($I21,$A:$A,B:B) -> aguas | K21: =_xlfn.XLOOKUP($I21,$A:$A,C:C) -> 25 | L21: =_xlfn.XLOOKUP($I21,$A:$A,D:D) -> 10 | M21: =_xlfn.XLOOKUP($I21,$A:$A,E:E) -> L1
A22: 21 | B22: al | C22: 1055 | D22: 13 | E22: L1 | I22: 442 | J22: =_xlfn.XLOOKUP($I22,$A:$A,B:B) -> ahora | K22: =_xlfn.XLOOKUP($I22,$A:$A,C:C) -> 40 | L22: =_xlfn.XLOOKUP($I22,$A:$A,D:D) -> 14 | M22: =_xlfn.XLOOKUP($I22,$A:$A,E:E) -> L1
I23: 699 | J23: =_xlfn.XLOOKUP($I23,$A:$A,B:B) -> aire | K23: =_xlfn.XLOOKUP($I23,$A:$A,C:C) -> 28 | L23: =_xlfn.XLOOKUP($I23,$A:$A,D:D) -> 14 | M23: =_xlfn.XLOOKUP($I23,$A:$A,E:E) -> L1
A24: 23 | B24: fue | C24: 944 | D24: 9 | E24: L1 | I24: 21 | J24: =_xlfn.XLOOKUP($I24,$A:$A,B:B) -> al | K24: =_xlfn.XLOOKUP($I24,$A:$A,C:C) -> 1055 | L24: =_xlfn.XLOOKUP($I24,$A:$A,D:D) -> 13 | M24: =_xlfn.XLOOKUP($I24,$A:$A,E:E) -> L1
A25: 24 | B25: no | C25: 891 | D25: 12 | E25: L1 | I25: 228 | J25: =_xlfn.XLOOKUP($I25,$A:$A,B:B) -> álbum | K25: =_xlfn.XLOOKUP($I25,$A:$A,C:C) -> 68 | L25: =_xlfn.XLOOKUP($I25,$A:$A,D:D) -> 3 | M25: =_xlfn.XLOOKUP($I25,$A:$A,E:E) -> L2
I26: 856 | J26: =_xlfn.XLOOKUP($I26,$A:$A,B:B) -> alemán | K26: =_xlfn.XLOOKUP($I26,$A:$A,C:C) -> 23 | L26: =_xlfn.XLOOKUP($I26,$A:$A,D:D) -> 12 | M26: =_xlfn.XLOOKUP($I26,$A:$A,E:E) -> L1
A27: 26 | B27: más | C27: 855 | D27: 2 | E27: L1 | I27: 572 | J27: =_xlfn.XLOOKUP($I27,$A:$A,B:B) -> Alemania | K27: =_xlfn.XLOOKUP($I27,$A:$A,C:C) -> 32 | L27: =_xlfn.XLOOKUP($I27,$A:$A,D:D) -> 1 | M27: =_xlfn.XLOOKUP($I27,$A:$A,E:E) -> L1
A28: 27 | B28: sus | C28: 663 | D28: 12 | E28: L1 | I28: 547 | J28: =_xlfn.XLOOKUP($I28,$A:$A,B:B) -> algo | K28: =_xlfn.XLOOKUP($I28,$A:$A,C:C) -> 34 | L28: =_xlfn.XLOOKUP($I28,$A:$A,D:D) -> 13 | M28: =_xlfn.XLOOKUP($I28,$A:$A,E:E) -> L1
A29: 28 | B29: lo | C29: 652 | D29: 15 | E29: L1 | I29: 766 | J29: =_xlfn.XLOOKUP($I29,$A:$A,B:B) -> algún | K29: =_xlfn.XLOOKUP($I29,$A:$A,C:C) -> 26 | L29: =_xlfn.XLOOKUP($I29,$A:$A,D:D) -> 15 | M29: =_xlfn.XLOOKUP($I29,$A:$A,E:E) -> L1
A30: 29 | B30: o | C30: 458 | D30: 2 | E30: L1 | I30: 579 | J30: =_xlfn.XLOOKUP($I30,$A:$A,B:B) -> alguna | K30: =_xlfn.XLOOKUP($I30,$A:$A,C:C) -> 32 | L30: =_xlfn.XLOOKUP($I30,$A:$A,D:D) -> 12 | M30: =_xlfn.XLOOKUP($I30,$A:$A,E:E) -> L1
A31: 30 | B31: también | C31: 390 | D31: 12 | E31: L1 | I31: 234 | J31: =_xlfn.XLOOKUP($I31,$A:$A,B:B) -> algunas | K31: =_xlfn.XLOOKUP($I31,$A:$A,C:C) -> 67 | L31: =_xlfn.XLOOKUP($I31,$A:$A,D:D) -> 15 | M31: =_xlfn.XLOOKUP($I31,$A:$A,E:E) -> L1
A32: 31 | B32: dos | C32: 379 | D32: 4 | E32: L1 | I32: 400 | J32: =_xlfn.XLOOKUP($I32,$A:$A,B:B) -> allí | K32: =_xlfn.XLOOKUP($I32,$A:$A,C:C) -> 0 | L32: =_xlfn.XLOOKUP($I32,$A:$A,D:D) -> 13 | M32: =_xlfn.XLOOKUP($I32,$A:$A,E:E) -> L1
I33: 275 | J33: =_xlfn.XLOOKUP($I33,$A:$A,B:B) -> alrededor | K33: =_xlfn.XLOOKUP($I33,$A:$A,C:C) -> 58 | L33: =_xlfn.XLOOKUP($I33,$A:$A,D:D) -> 10 | M33: =_xlfn.XLOOKUP($I33,$A:$A,E:E) -> L2
A34: 33 | B34: entre | C34: 373 | D34: 12 | E34: L2 | I34: 384 | J34: =_xlfn.XLOOKUP($I34,$A:$A,B:B) -> alta | K34: =_xlfn.XLOOKUP($I34,$A:$A,C:C) -> 45 | L34: =_xlfn.XLOOKUP($I34,$A:$A,D:D) -> 11 | M34: =_xlfn.XLOOKUP($I34,$A:$A,E:E) -> L1
A35: 34 | B35: años | C35: 362 | D35: 9 | E35: L1 | I35: 373 | J35: =_xlfn.XLOOKUP($I35,$A:$A,B:B) -> alto | K35: =_xlfn.XLOOKUP($I35,$A:$A,C:C) -> 46 | L35: =_xlfn.XLOOKUP($I35,$A:$A,D:D) -> 6 | M35: =_xlfn.XLOOKUP($I35,$A:$A,E:E) -> L1
A36: 35 | B36: pero | C36: 359 | D36: 12 | E36: L1 | I36: 730 | J36: =_xlfn.XLOOKUP($I36,$A:$A,B:B) -> altura | K36: =_xlfn.XLOOKUP($I36,$A:$A,C:C) -> 27 | L36: =_xlfn.XLOOKUP($I36,$A:$A,D:D) -> 10 | M36: =_xlfn.XLOOKUP($I36,$A:$A,E:E) -> L2
A37: 36 | B37: ha | C37: 334 | D37: 9 | E37: L3 | I37: 600 | J37: =_xlfn.XLOOKUP($I37,$A:$A,B:B) -> ambas | K37: =_xlfn.XLOOKUP($I37,$A:$A,C:C) -> 31 | L37: =_xlfn.XLOOKUP($I37,$A:$A,D:D) -> 12 | M37: =_xlfn.XLOOKUP($I37,$A:$A,E:E) -> L3
A38: 37 | B38: este | C38: 330 | D38: 13 | E38: L1 | I38: 310 | J38: =_xlfn.XLOOKUP($I38,$A:$A,B:B) -> ambos | K38: =_xlfn.XLOOKUP($I38,$A:$A,C:C) -> 54 | L38: =_xlfn.XLOOKUP($I38,$A:$A,D:D) -> 12 | M38: =_xlfn.XLOOKUP($I38,$A:$A,E:E) -> L2
A39: 38 | B39: sobre | C39: 313 | D39: 12 | E39: L2 | I39: 469 | J39: =_xlfn.XLOOKUP($I39,$A:$A,B:B) -> América | K39: =_xlfn.XLOOKUP($I39,$A:$A,C:C) -> 38 | L39: =_xlfn.XLOOKUP($I39,$A:$A,D:D) -> 10 | M39: =_xlfn.XLOOKUP($I39,$A:$A,E:E) -> L1
A40: 39 | B40: le | C40: 311 | D40: 12 | E40: L1 | I40: 666 | J40: =_xlfn.XLOOKUP($I40,$A:$A,B:B) -> amigos | K40: =_xlfn.XLOOKUP($I40,$A:$A,C:C) -> 29 | L40: =_xlfn.XLOOKUP($I40,$A:$A,D:D) -> 13 | M40: =_xlfn.XLOOKUP($I40,$A:$A,E:E) -> L1
A41: 40 | B41: son | C41: 311 | D41: 2 | E41: L1 | I41: 908 | J41: =_xlfn.XLOOKUP($I41,$A:$A,B:B) -> and | K41: =_xlfn.XLOOKUP($I41,$A:$A,C:C) -> 22 | L41: =_xlfn.XLOOKUP($I41,$A:$A,D:D) -> 15 | M41: =_xlfn.XLOOKUP($I41,$A:$A,E:E) -> L1
A42: 41 | B42: hasta | C42: 294 | D42: 9 | E42: L1 | I42: 44 | J42: =_xlfn.XLOOKUP($I42,$A:$A,B:B) -> año | K42: =_xlfn.XLOOKUP($I42,$A:$A,C:C) -> 280 | L42: =_xlfn.XLOOKUP($I42,$A:$A,D:D) -> 1 | M42: =_xlfn.XLOOKUP($I42,$A:$A,E:E) -> L1
A43: 42 | B43: ser | C43: 292 | D43: 12 | E43: L1 | I43: 34 | J43: =_xlfn.XLOOKUP($I43,$A:$A,B:B) -> años | K43: =_xlfn.XLOOKUP($I43,$A:$A,C:C) -> 362 | L43: =_xlfn.XLOOKUP($I43,$A:$A,D:D) -> 9 | M43: =_xlfn.XLOOKUP($I43,$A:$A,E:E) -> L1
A44: 43 | B44: era | C44: 283 | D44: 9 | E44: L1 | I44: 521 | J44: =_xlfn.XLOOKUP($I44,$A:$A,B:B) -> ante | K44: =_xlfn.XLOOKUP($I44,$A:$A,C:C) -> 35 | L44: =_xlfn.XLOOKUP($I44,$A:$A,D:D) -> 8 | M44: =_xlfn.XLOOKUP($I44,$A:$A,E:E) -> L2
A45: 44 | B45: año | C45: 280 | D45: 1 | E45: L1 | I45: 425 | J45: =_xlfn.XLOOKUP($I45,$A:$A,B:B) -> anterior | K45: =_xlfn.XLOOKUP($I45,$A:$A,C:C) -> 41 | L45: =_xlfn.XLOOKUP($I45,$A:$A,D:D) -> 9 | M45: =_xlfn.XLOOKUP($I45,$A:$A,E:E) -> L2
I46: 991 | J46: =_xlfn.XLOOKUP($I46,$A:$A,B:B) -> anteriores | K46: =_xlfn.XLOOKUP($I46,$A:$A,C:C) -> 21 | L46: =_xlfn.XLOOKUP($I46,$A:$A,D:D) -> 9 | M46: =_xlfn.XLOOKUP($I46,$A:$A,E:E) -> L2
A47: 46 | B47: parte | C47: 267 | D47: 5 | E47: L1 | I47: 106 | J47: =_xlfn.XLOOKUP($I47,$A:$A,B:B) -> antes | K47: =_xlfn.XLOOKUP($I47,$A:$A,C:C) -> 120 | L47: =_xlfn.XLOOKUP($I47,$A:$A,D:D) -> 9 | M47: =_xlfn.XLOOKUP($I47,$A:$A,E:E) -> L1
A48: 47 | B48: esta | C48: 264 | D48: 13 | E48: L1 | I48: 806 | J48: =_xlfn.XLOOKUP($I48,$A:$A,B:B) -> antigua | K48: =_xlfn.XLOOKUP($I48,$A:$A,C:C) -> 25 | L48: =_xlfn.XLOOKUP($I48,$A:$A,D:D) -> 9 | M48: =_xlfn.XLOOKUP($I48,$A:$A,E:E) -> L2
A49: 48 | B49: donde | C49: 257 | D49: 10 | E49: L1 | I49: 731 | J49: =_xlfn.XLOOKUP($I49,$A:$A,B:B) -> antiguo | K49: =_xlfn.XLOOKUP($I49,$A:$A,C:C) -> 27 | L49: =_xlfn.XLOOKUP($I49,$A:$A,D:D) -> 9 | M49: =_xlfn.XLOOKUP($I49,$A:$A,E:E) -> L2
A50: 49 | B50: desde | C50: 249 | D50: 9 | E50: L1 | I50: 947 | J50: =_xlfn.XLOOKUP($I50,$A:$A,B:B) -> Antonio | K50: =_xlfn.XLOOKUP($I50,$A:$A,C:C) -> 22 | L50: =_xlfn.XLOOKUP($I50,$A:$A,D:D) -> 3 | M50: =_xlfn.XLOOKUP($I50,$A:$A,E:E) -> L1
A51: 50 | B51: después | C51: 245 | D51: 9 | E51: L1 | I51: 601 | J51: =_xlfn.XLOOKUP($I51,$A:$A,B:B) -> anunció | K51: =_xlfn.XLOOKUP($I51,$A:$A,C:C) -> 31 | L51: =_xlfn.XLOOKUP($I51,$A:$A,D:D) -> 1 | M51: =_xlfn.XLOOKUP($I51,$A:$A,E:E) -> L3
I52: 602 | J52: =_xlfn.XLOOKUP($I52,$A:$A,B:B) -> aparece | K52: =_xlfn.XLOOKUP($I52,$A:$A,C:C) -> 31 | L52: =_xlfn.XLOOKUP($I52,$A:$A,D:D) -> 3 | M52: =_xlfn.XLOOKUP($I52,$A:$A,E:E) -> L2
A53: 52 | B53: puede | C53: 236 | D53: 6 | E53: L1 | I53: 487 | J53: =_xlfn.XLOOKUP($I53,$A:$A,B:B) -> apoyo | K53: =_xlfn.XLOOKUP($I53,$A:$A,C:C) -> 37 | L53: =_xlfn.XLOOKUP($I53,$A:$A,D:D) -> 12 | M53: =_xlfn.XLOOKUP($I53,$A:$A,E:E) -> L2
A54: 53 | B54: sin | C54: 236 | D54: 8 | E54: L1 | I54: 323 | J54: =_xlfn.XLOOKUP($I54,$A:$A,B:B) -> aproximadamente | K54: =_xlfn.XLOOKUP($I54,$A:$A,C:C) -> 51 | L54: =_xlfn.XLOOKUP($I54,$A:$A,D:D) -> 2 | M54: =_xlfn.XLOOKUP($I54,$A:$A,E:E) -> L3
A55: 54 | B55: durante | C55: 230 | D55: 9 | E55: L1 | I55: 857 | J55: =_xlfn.XLOOKUP($I55,$A:$A,B:B) -> aquel | K55: =_xlfn.XLOOKUP($I55,$A:$A,C:C) -> 23 | L55: =_xlfn.XLOOKUP($I55,$A:$A,D:D) -> 15 | M55: =_xlfn.XLOOKUP($I55,$A:$A,E:E) -> L1
A56: 55 | B56: tiene | C56: 225 | D56: 2 | E56: L1 | I56: 992 | J56: =_xlfn.XLOOKUP($I56,$A:$A,B:B) -> aquellos | K56: =_xlfn.XLOOKUP($I56,$A:$A,C:C) -> 21 | L56: =_xlfn.XLOOKUP($I56,$A:$A,D:D) -> 15 | M56: =_xlfn.XLOOKUP($I56,$A:$A,E:E) -> L1
I57: 667 | J57: =_xlfn.XLOOKUP($I57,$A:$A,B:B) -> aquí | K57: =_xlfn.XLOOKUP($I57,$A:$A,C:C) -> 29 | L57: =_xlfn.XLOOKUP($I57,$A:$A,D:D) -> 10 | M57: =_xlfn.XLOOKUP($I57,$A:$A,E:E) -> L1
A58: 57 | B58: ya | C58: 211 | D58: 15 | E58: L1 | I58: 370 | J58: =_xlfn.XLOOKUP($I58,$A:$A,B:B) -> área | K58: =_xlfn.XLOOKUP($I58,$A:$A,C:C) -> 46 | L58: =_xlfn.XLOOKUP($I58,$A:$A,D:D) -> 10 | M58: =_xlfn.XLOOKUP($I58,$A:$A,E:E) -> L2
I59: 847 | J59: =_xlfn.XLOOKUP($I59,$A:$A,B:B) -> áreas | K59: =_xlfn.XLOOKUP($I59,$A:$A,C:C) -> 24 | L59: =_xlfn.XLOOKUP($I59,$A:$A,D:D) -> 10 | M59: =_xlfn.XLOOKUP($I59,$A:$A,E:E) -> L2
A60: 59 | B60: cuando | C60: 205 | D60: 9 | E60: L1 | I60: 598 | J60: =_xlfn.XLOOKUP($I60,$A:$A,B:B) -> Argentina | K60: =_xlfn.XLOOKUP($I60,$A:$A,C:C) -> 31 | L60: =_xlfn.XLOOKUP($I60,$A:$A,D:D) -> 1 | M60: =_xlfn.XLOOKUP($I60,$A:$A,E:E) -> L1
A61: 60 | B61: muy | C61: 205 | D61: 14 | E61: L1 | I61: 503 | J61: =_xlfn.XLOOKUP($I61,$A:$A,B:B) -> arte | K61: =_xlfn.XLOOKUP($I61,$A:$A,C:C) -> 36 | L61: =_xlfn.XLOOKUP($I61,$A:$A,D:D) -> 3 | M61: =_xlfn.XLOOKUP($I61,$A:$A,E:E) -> L2
A62: 61 | B62: había | C62: 203 | D62: 9 | E62: L1 | I62: 807 | J62: =_xlfn.XLOOKUP($I62,$A:$A,B:B) -> artículos | K62: =_xlfn.XLOOKUP($I62,$A:$A,C:C) -> 25 | L62: =_xlfn.XLOOKUP($I62,$A:$A,D:D) -> 1 | M62: =_xlfn.XLOOKUP($I62,$A:$A,E:E) -> L3
A63: 62 | B63: está | C63: 199 | D63: 11 | E63: L1 | I63: 95 | J63: =_xlfn.XLOOKUP($I63,$A:$A,B:B) -> así | K63: =_xlfn.XLOOKUP($I63,$A:$A,C:C) -> 133 | L63: =_xlfn.XLOOKUP($I63,$A:$A,D:D) -> 8 | M63: =_xlfn.XLOOKUP($I63,$A:$A,E:E) -> L1
A64: 63 | B64: vez | C64: 197 | D64: 9 | E64: L1 | I64: 988 | J64: =_xlfn.XLOOKUP($I64,$A:$A,B:B) -> Asimismo | K64: =_xlfn.XLOOKUP($I64,$A:$A,C:C) -> 21 | L64: =_xlfn.XLOOKUP($I64,$A:$A,D:D) -> 8 | M64: =_xlfn.XLOOKUP($I64,$A:$A,E:E) -> L3
A65: 64 | B65: primera | C65: 191 | D65: 4 | E65: L1 | I65: 472 | J65: =_xlfn.XLOOKUP($I65,$A:$A,B:B) -> ataque | K65: =_xlfn.XLOOKUP($I65,$A:$A,C:C) -> 38 | L65: =_xlfn.XLOOKUP($I65,$A:$A,D:D) -> 4 | M65: =_xlfn.XLOOKUP($I65,$A:$A,E:E) -> L2
A66: 65 | B66: mismo | C66: 188 | D66: 12 | E66: L1 | I66: 700 | J66: =_xlfn.XLOOKUP($I66,$A:$A,B:B) -> atención | K66: =_xlfn.XLOOKUP($I66,$A:$A,C:C) -> 28 | L66: =_xlfn.XLOOKUP($I66,$A:$A,D:D) -> 11 | M66: =_xlfn.XLOOKUP($I66,$A:$A,E:E) -> L2
A67: 66 | B67: fueron | C67: 183 | D67: 9 | E67: L1 | I67: 269 | J67: =_xlfn.XLOOKUP($I67,$A:$A,B:B) -> aún | K67: =_xlfn.XLOOKUP($I67,$A:$A,C:C) -> 60 | L67: =_xlfn.XLOOKUP($I67,$A:$A,D:D) -> 9 | M67: =_xlfn.XLOOKUP($I67,$A:$A,E:E) -> L2
A68: 67 | B68: tiempo | C68: 183 | D68: 9 | E68: L1 | I68: 117 | J68: =_xlfn.XLOOKUP($I68,$A:$A,B:B) -> aunque | K68: =_xlfn.XLOOKUP($I68,$A:$A,C:C) -> 107 | L68: =_xlfn.XLOOKUP($I68,$A:$A,D:D) -> 12 | M68: =_xlfn.XLOOKUP($I68,$A:$A,E:E) -> L2
A69: 68 | B69: sido | C69: 176 | D69: 13 | E69: L1 | I69: 456 | J69: =_xlfn.XLOOKUP($I69,$A:$A,B:B) -> ayuda | K69: =_xlfn.XLOOKUP($I69,$A:$A,C:C) -> 39 | L69: =_xlfn.XLOOKUP($I69,$A:$A,D:D) -> 11 | M69: =_xlfn.XLOOKUP($I69,$A:$A,E:E) -> L1
A70: 69 | B70: otros | C70: 175 | D70: 12 | E70: L1 | I70: 993 | J70: =_xlfn.XLOOKUP($I70,$A:$A,B:B) -> baja | K70: =_xlfn.XLOOKUP($I70,$A:$A,C:C) -> 21 | L70: =_xlfn.XLOOKUP($I70,$A:$A,D:D) -> 11 | M70: =_xlfn.XLOOKUP($I70,$A:$A,E:E) -> L2
A71: 70 | B71: ciudad | C71: 171 | D71: 10 | E71: L1 | I71: 119 | J71: =_xlfn.XLOOKUP($I71,$A:$A,B:B) -> bajo | K71: =_xlfn.XLOOKUP($I71,$A:$A,C:C) -> 106 | L71: =_xlfn.XLOOKUP($I71,$A:$A,D:D) -> 8 | M71: =_xlfn.XLOOKUP($I71,$A:$A,E:E) -> L1
... A82: 81 | B82: nombre | C82: 150 | D82: 3 | E82: L1 | I82: 504 | J82: =_xlfn.XLOOKUP($I82,$A:$A,B:B) -> cabo | K82: =_xlfn.XLOOKUP($I82,$A:$A,C:C) -> 36 | L82: =_xlfn.XLOOKUP($I82,$A:$A,D:D) -> 8 | M82: =_xlfn.XLOOKUP($I82,$A:$A,E:E) -> L2
I83: 76 | J83: =_xlfn.XLOOKUP($I83,$A:$A,B:B) -> cada | K83: =_xlfn.XLOOKUP($I83,$A:$A,C:C) -> 162 | L83: =_xlfn.XLOOKUP($I83,$A:$A,D:D) -> 5 | M83: =_xlfn.XLOOKUP($I83,$A:$A,E:E) -> L1
A84: 83 | B84: e | C84: 147 | D84: 12 | E84: L1 | I84: 668 | J84: =_xlfn.XLOOKUP($I84,$A:$A,B:B) -> calidad | K84: =_xlfn.XLOOKUP($I84,$A:$A,C:C) -> 29 | L84: =_xlfn.XLOOKUP($I84,$A:$A,D:D) -> 5 | M84: =_xlfn.XLOOKUP($I84,$A:$A,E:E) -> L2
I85: 701 | J85: =_xlfn.XLOOKUP($I85,$A:$A,B:B) -> calle | K85: =_xlfn.XLOOKUP($I85,$A:$A,C:C) -> 28 | L85: =_xlfn.XLOOKUP($I85,$A:$A,D:D) -> 12 | M85: =_xlfn.XLOOKUP($I85,$A:$A,E:E) -> L1
I86: 311 | J86: =_xlfn.XLOOKUP($I86,$A:$A,B:B) -> cambio | K86: =_xlfn.XLOOKUP($I86,$A:$A,C:C) -> 54 | L86: =_xlfn.XLOOKUP($I86,$A:$A,D:D) -> 2 | M86: =_xlfn.XLOOKUP($I86,$A:$A,E:E) -> L2
A87: 86 | B87: mayor | C87: 140 | D87: 2 | E87: L2 | I87: 912 | J87: =_xlfn.XLOOKUP($I87,$A:$A,B:B) -> cambios | K87: =_xlfn.XLOOKUP($I87,$A:$A,C:C) -> 22 | L87: =_xlfn.XLOOKUP($I87,$A:$A,D:D) -> 2 | M87: =_xlfn.XLOOKUP($I87,$A:$A,E:E) -> L2
A88: 87 | B88: tanto | C88: 137 | D88: 4 | E88: L2 | I88: 488 | J88: =_xlfn.XLOOKUP($I88,$A:$A,B:B) -> camino | K88: =_xlfn.XLOOKUP($I88,$A:$A,C:C) -> 37 | L88: =_xlfn.XLOOKUP($I88,$A:$A,D:D) -> 13 | M88: =_xlfn.XLOOKUP($I88,$A:$A,E:E) -> L1
A89: 88 | B89: todos | C89: 137 | D89: 12 | E89: L1 | I89: 473 | J89: =_xlfn.XLOOKUP($I89,$A:$A,B:B) -> campaña | K89: =_xlfn.XLOOKUP($I89,$A:$A,C:C) -> 38 | L89: =_xlfn.XLOOKUP($I89,$A:$A,D:D) -> 1 | M89: =_xlfn.XLOOKUP($I89,$A:$A,E:E) -> L2
A90: 89 | B90: pueden | C90: 136 | D90: 6 | E90: L1 | I90: 994 | J90: =_xlfn.XLOOKUP($I90,$A:$A,B:B) -> campeón | K90: =_xlfn.XLOOKUP($I90,$A:$A,C:C) -> 21 | L90: =_xlfn.XLOOKUP($I90,$A:$A,D:D) -> 4 | M90: =_xlfn.XLOOKUP($I90,$A:$A,E:E) -> L2
A91: 90 | B91: vida | C91: 135 | D91: 11 | E91: L1 | I91: 913 | J91: =_xlfn.XLOOKUP($I91,$A:$A,B:B) -> campeonato | K91: =_xlfn.XLOOKUP($I91,$A:$A,C:C) -> 22 | L91: =_xlfn.XLOOKUP($I91,$A:$A,D:D) -> 4 | M91: =_xlfn.XLOOKUP($I91,$A:$A,E:E) -> L2
I92: 312 | J92: =_xlfn.XLOOKUP($I92,$A:$A,B:B) -> campo | K92: =_xlfn.XLOOKUP($I92,$A:$A,C:C) -> 53 | L92: =_xlfn.XLOOKUP($I92,$A:$A,D:D) -> 10 | M92: =_xlfn.XLOOKUP($I92,$A:$A,E:E) -> L2
A93: 92 | B93: han | C93: 134 | D93: 9 | E93: L1 | I93: 580 | J93: =_xlfn.XLOOKUP($I93,$A:$A,B:B) -> canal | K93: =_xlfn.XLOOKUP($I93,$A:$A,C:C) -> 32 | L93: =_xlfn.XLOOKUP($I93,$A:$A,D:D) -> 6 | M93: =_xlfn.XLOOKUP($I93,$A:$A,E:E) -> L2
A94: 93 | B94: mientras | C94: 134 | D94: 9 | E94: L2 | I94: 267 | J94: =_xlfn.XLOOKUP($I94,$A:$A,B:B) -> canción | K94: =_xlfn.XLOOKUP($I94,$A:$A,C:C) -> 60 | L94: =_xlfn.XLOOKUP($I94,$A:$A,D:D) -> 3 | M94: =_xlfn.XLOOKUP($I94,$A:$A,E:E) -> L2
A95: 94 | B95: él | C95: 134 | D95: 15 | E95: L1 | I95: 354 | J95: =_xlfn.XLOOKUP($I95,$A:$A,B:B) -> canciones | K95: =_xlfn.XLOOKUP($I95,$A:$A,C:C) -> 48 | L95: =_xlfn.XLOOKUP($I95,$A:$A,D:D) -> 3 | M95: =_xlfn.XLOOKUP($I95,$A:$A,E:E) -> L2
A96: 95 | B96: así | C96: 133 | D96: 8 | E96: L1 | I96: 305 | J96: =_xlfn.XLOOKUP($I96,$A:$A,B:B) -> cantidad | K96: =_xlfn.XLOOKUP($I96,$A:$A,C:C) -> 55 | L96: =_xlfn.XLOOKUP($I96,$A:$A,D:D) -> 2 | M96: =_xlfn.XLOOKUP($I96,$A:$A,E:E) -> L2
I97: 391 | J97: =_xlfn.XLOOKUP($I97,$A:$A,B:B) -> capacidad | K97: =_xlfn.XLOOKUP($I97,$A:$A,C:C) -> 44 | L97: =_xlfn.XLOOKUP($I97,$A:$A,D:D) -> 6 | M97: =_xlfn.XLOOKUP($I97,$A:$A,E:E) -> L2
A98: 97 | B98: nuevo | C98: 132 | D98: 6 | E98: L1 | I98: 669 | J98: =_xlfn.XLOOKUP($I98,$A:$A,B:B) -> capaz | K98: =_xlfn.XLOOKUP($I98,$A:$A,C:C) -> 29 | L98: =_xlfn.XLOOKUP($I98,$A:$A,D:D) -> 7 | M98: =_xlfn.XLOOKUP($I98,$A:$A,E:E) -> L2
A99: 98 | B99: si | C99: 131 | D99: 8 | E99: L1 | I99: 522 | J99: =_xlfn.XLOOKUP($I99,$A:$A,B:B) -> capital | K99: =_xlfn.XLOOKUP($I99,$A:$A,C:C) -> 35 | L99: =_xlfn.XLOOKUP($I99,$A:$A,D:D) -> 2 | M99: =_xlfn.XLOOKUP($I99,$A:$A,E:E) -> L2
A100: 99 | B100: grupo | C100: 127 | D100: 5 | E100: L2 | I100: 732 | J100: =_xlfn.XLOOKUP($I100,$A:$A,B:B) -> carácter | K100: =_xlfn.XLOOKUP($I100,$A:$A,C:C) -> 27 | L100: =_xlfn.XLOOKUP($I100,$A:$A,D:D) -> 12 | M100: =_xlfn.XLOOKUP($I100,$A:$A,E:E) -> L3
I101: 443 | J101: =_xlfn.XLOOKUP($I101,$A:$A,B:B) -> características | K101: =_xlfn.XLOOKUP($I101,$A:$A,C:C) -> 40 | L101: =_xlfn.XLOOKUP($I101,$A:$A,D:D) -> 6 | M101: =_xlfn.XLOOKUP($I101,$A:$A,E:E) -> L3
A102: 101 | B102: día | C102: 125 | D102: 13 | E102: L1 | I102: 670 | J102: =_xlfn.XLOOKUP($I102,$A:$A,B:B) -> carga | K102: =_xlfn.XLOOKUP($I102,$A:$A,C:C) -> 29 | L102: =_xlfn.XLOOKUP($I102,$A:$A,D:D) -> 5 | M102: =_xlfn.XLOOKUP($I102,$A:$A,E:E) -> L2
A103: 102 | B103: contra | C103: 124 | D103: 8 | E103: L1 | I103: 313 | J103: =_xlfn.XLOOKUP($I103,$A:$A,B:B) -> cargo | K103: =_xlfn.XLOOKUP($I103,$A:$A,C:C) -> 53 | L103: =_xlfn.XLOOKUP($I103,$A:$A,D:D) -> 5 | M103: =_xlfn.XLOOKUP($I103,$A:$A,E:E) -> L2
A104: 103 | B104: otras | C104: 123 | D104: 12 | E104: L1 | I104: 848 | J104: =_xlfn.XLOOKUP($I104,$A:$A,B:B) -> Carlos | K104: =_xlfn.XLOOKUP($I104,$A:$A,C:C) -> 24 | L104: =_xlfn.XLOOKUP($I104,$A:$A,D:D) -> 3 | M104: =_xlfn.XLOOKUP($I104,$A:$A,E:E) -> L1
A105: 104 | B105: ese | C105: 122 | D105: 13 | E105: L1 | I105: 238 | J105: =_xlfn.XLOOKUP($I105,$A:$A,B:B) -> carrera | K105: =_xlfn.XLOOKUP($I105,$A:$A,C:C) -> 66 | L105: =_xlfn.XLOOKUP($I105,$A:$A,D:D) -> 7 | M105: =_xlfn.XLOOKUP($I105,$A:$A,E:E) -> L2
I106: 147 | J106: =_xlfn.XLOOKUP($I106,$A:$A,B:B) -> casa | K106: =_xlfn.XLOOKUP($I106,$A:$A,C:C) -> 94 | L106: =_xlfn.XLOOKUP($I106,$A:$A,D:D) -> 13 | M106: =_xlfn.XLOOKUP($I106,$A:$A,E:E) -> L1
A107: 106 | B107: antes | C107: 120 | D107: 9 | E107: L1 | I107: 671 | J107: =_xlfn.XLOOKUP($I107,$A:$A,B:B) -> casas | K107: =_xlfn.XLOOKUP($I107,$A:$A,C:C) -> 29 | L107: =_xlfn.XLOOKUP($I107,$A:$A,D:D) -> 13 | M107: =_xlfn.XLOOKUP($I107,$A:$A,E:E) -> L1
I108: 230 | J108: =_xlfn.XLOOKUP($I108,$A:$A,B:B) -> casi | K108: =_xlfn.XLOOKUP($I108,$A:$A,C:C) -> 67 | L108: =_xlfn.XLOOKUP($I108,$A:$A,D:D) -> 12 | M108: =_xlfn.XLOOKUP($I108,$A:$A,E:E) -> L1
I109: 194 | J109: =_xlfn.XLOOKUP($I109,$A:$A,B:B) -> caso | K109: =_xlfn.XLOOKUP($I109,$A:$A,C:C) -> 79 | L109: =_xlfn.XLOOKUP($I109,$A:$A,D:D) -> 8 | M109: =_xlfn.XLOOKUP($I109,$A:$A,E:E) -> L2
I110: 859 | J110: =_xlfn.XLOOKUP($I110,$A:$A,B:B) -> casó | K110: =_xlfn.XLOOKUP($I110,$A:$A,C:C) -> 23 | L110: =_xlfn.XLOOKUP($I110,$A:$A,D:D) -> 12 | M110: =_xlfn.XLOOKUP($I110,$A:$A,E:E) -> L1
...

Sheet Final output
A1: WORD ID | B1: word | C1: Frequency | D1: CAT ID | E1: LEVEL ID
A2: 1 | B2: de | C2: 15226 | D2: 1 | E2: L1
A3: 2 | B3: la | C3: 7493 | D3: 12 | E3: L1
A4: 3 | B4: en | C4: 5973 | D4: 10 | E4: L1
A5: 4 | B5: el | C5: 5435 | D5: 12 | E5: L1
A6: 5 | B6: y | C6: 5422 | D6: 12 | E6: L1
A7: 6 | B7: que | C7: 4171 | D7: 12 | E7: L1
A8: 7 | B8: se | C8: 2845 | D8: 12 | E8: L1
A9: 8 | B9: los | C9: 2800 | D9: 12 | E9: L1
A10: 9 | B10: del | C10: 2645 | D10: 1 | E10: L1
A11: 10 | B11: un | C11: 2205 | D11: 12 | E11: L1
A12: 11 | B12: su | C12: 2051 | D12: 5 | E12: L1
A13: 12 | B13: una | C13: 2023 | D13: 12 | E13: L1
... A912: 911 | B912: volvió | C912: 0 | D912: 9 | E912: L2
